{
"meta":{"test_sets":[],"test_metrics":[],"learn_metrics":[{"best_value":"Min","name":"RMSE"}],"launch_mode":"Train","parameters":"","iteration_count":1000,"learn_sets":["learn"],"name":"experiment"},
"iterations":[
{"learn":[1821934.45],"iteration":0,"passed_time":0.05966082977,"remaining_time":59.60116894},
{"learn":[1818913.403],"iteration":1,"passed_time":0.06050251572,"remaining_time":30.19075534},
{"learn":[1815488.099],"iteration":2,"passed_time":0.0615094056,"remaining_time":20.4416258},
{"learn":[1813360.216],"iteration":3,"passed_time":0.06245217219,"remaining_time":15.55059088},
{"learn":[1811834.072],"iteration":4,"passed_time":0.06345064564,"remaining_time":12.62667848},
{"learn":[1809975.575],"iteration":5,"passed_time":0.06430749785,"remaining_time":10.65360881},
{"learn":[1807935.131],"iteration":6,"passed_time":0.06529638821,"remaining_time":9.26275907},
{"learn":[1806044.037],"iteration":7,"passed_time":0.06627502885,"remaining_time":8.218103577},
{"learn":[1804090.226],"iteration":8,"passed_time":0.0671413808,"remaining_time":7.393012042},
{"learn":[1802425.267],"iteration":9,"passed_time":0.06807531429,"remaining_time":6.739456115},
{"learn":[1800875.468],"iteration":10,"passed_time":0.06908549576,"remaining_time":6.211414119},
{"learn":[1798561.452],"iteration":11,"passed_time":0.06997747203,"remaining_time":5.761478531},
{"learn":[1796875.056],"iteration":12,"passed_time":0.07081419978,"remaining_time":5.376431937},
{"learn":[1795773.74],"iteration":13,"passed_time":0.07165076086,"remaining_time":5.046260729},
{"learn":[1795313.113],"iteration":14,"passed_time":0.07258786093,"remaining_time":4.766602868},
{"learn":[1794084.032],"iteration":15,"passed_time":0.0735227944,"remaining_time":4.521651856},
{"learn":[1792813.823],"iteration":16,"passed_time":0.07454739215,"remaining_time":4.310593322},
{"learn":[1790525.426],"iteration":17,"passed_time":0.0754275354,"remaining_time":4.114991098},
{"learn":[1789020.94],"iteration":18,"passed_time":0.07631867837,"remaining_time":3.940453867},
{"learn":[1788565.495],"iteration":19,"passed_time":0.07714423974,"remaining_time":3.780067747},
{"learn":[1787579.426],"iteration":20,"passed_time":0.07799375881,"remaining_time":3.635994756},
{"learn":[1786482.728],"iteration":21,"passed_time":0.07879323755,"remaining_time":3.50271756},
{"learn":[1785603.51],"iteration":22,"passed_time":0.07961750729,"remaining_time":3.382013244},
{"learn":[1784783.532],"iteration":23,"passed_time":0.08061198084,"remaining_time":3.278220554},
{"learn":[1783629.268],"iteration":24,"passed_time":0.08153978949,"remaining_time":3.18005179},
{"learn":[1783042.121],"iteration":25,"passed_time":0.08242964082,"remaining_time":3.08794116},
{"learn":[1782150.774],"iteration":26,"passed_time":0.08324870237,"remaining_time":3.000036571},
{"learn":[1780760.666],"iteration":27,"passed_time":0.08414105363,"remaining_time":2.920896576},
{"learn":[1779390.57],"iteration":28,"passed_time":0.08519694222,"remaining_time":2.852628651},
{"learn":[1778396.197],"iteration":29,"passed_time":0.08623333132,"remaining_time":2.788211046},
{"learn":[1778031.803],"iteration":30,"passed_time":0.08717709788,"remaining_time":2.72498735},
{"learn":[1777299.44],"iteration":31,"passed_time":0.08800761746,"remaining_time":2.662230428},
{"learn":[1776494.738],"iteration":32,"passed_time":0.08881322103,"remaining_time":2.602496507},
{"learn":[1775728.232],"iteration":33,"passed_time":0.08970207239,"remaining_time":2.548594174},
{"learn":[1774725.997],"iteration":34,"passed_time":0.09054542495,"remaining_time":2.496466717},
{"learn":[1773966.465],"iteration":35,"passed_time":0.0914058604,"remaining_time":2.447645817},
{"learn":[1772803.245],"iteration":36,"passed_time":0.09224037987,"remaining_time":2.40074286},
{"learn":[1771921.496],"iteration":37,"passed_time":0.09322481202,"remaining_time":2.360059715},
{"learn":[1771232.192],"iteration":38,"passed_time":0.09402891563,"remaining_time":2.316968921},
{"learn":[1770210.483],"iteration":39,"passed_time":0.0948873928,"remaining_time":2.277297427},
{"learn":[1769278.887],"iteration":40,"passed_time":0.09575036984,"remaining_time":2.239624504},
{"learn":[1768545.919],"iteration":41,"passed_time":0.09657397294,"remaining_time":2.202806335},
{"learn":[1767662.005],"iteration":42,"passed_time":0.09740911739,"remaining_time":2.167919194},
{"learn":[1766930.548],"iteration":43,"passed_time":0.09827430271,"remaining_time":2.135232577},
{"learn":[1765806.148],"iteration":44,"passed_time":0.09923198557,"remaining_time":2.105923249},
{"learn":[1765065.161],"iteration":45,"passed_time":0.1000474222,"remaining_time":2.074896539},
{"learn":[1764230.337],"iteration":46,"passed_time":0.1009431484,"remaining_time":2.046783413},
{"learn":[1763411.468],"iteration":47,"passed_time":0.1017698764,"remaining_time":2.018435882},
{"learn":[1762805.718],"iteration":48,"passed_time":0.1025416059,"remaining_time":1.990144228},
{"learn":[1761922.818],"iteration":49,"passed_time":0.1033447095,"remaining_time":1.963549481},
{"learn":[1760650.688],"iteration":50,"passed_time":0.1042706849,"remaining_time":1.940252548},
{"learn":[1759957.332],"iteration":51,"passed_time":0.105117954,"remaining_time":1.916381162},
{"learn":[1759289.971],"iteration":52,"passed_time":0.1060635955,"remaining_time":1.89513632},
{"learn":[1758885.016],"iteration":53,"passed_time":0.1070060705,"remaining_time":1.874587827},
{"learn":[1758105.271],"iteration":54,"passed_time":0.1078989217,"remaining_time":1.853899655},
{"learn":[1757499.656],"iteration":55,"passed_time":0.1088235638,"remaining_time":1.834454361},
{"learn":[1756823.897],"iteration":56,"passed_time":0.1096421253,"remaining_time":1.813903933},
{"learn":[1756437.756],"iteration":57,"passed_time":0.1106095163,"remaining_time":1.796451109},
{"learn":[1755344.912],"iteration":58,"passed_time":0.1114712434,"remaining_time":1.777871864},
{"learn":[1754519.547],"iteration":59,"passed_time":0.1125021326,"remaining_time":1.762533411},
{"learn":[1754284.667],"iteration":60,"passed_time":0.1133869841,"remaining_time":1.745416033},
{"learn":[1753046.195],"iteration":61,"passed_time":0.1141340475,"remaining_time":1.726737687},
{"learn":[1752443.999],"iteration":62,"passed_time":0.114931318,"remaining_time":1.709375317},
{"learn":[1751758.708],"iteration":63,"passed_time":0.115795545,"remaining_time":1.693509846},
{"learn":[1750990.381],"iteration":64,"passed_time":0.1166188981,"remaining_time":1.677517996},
{"learn":[1750151.688],"iteration":65,"passed_time":0.1173815445,"remaining_time":1.661126705},
{"learn":[1749240.499],"iteration":66,"passed_time":0.1182441049,"remaining_time":1.646593281},
{"learn":[1748402.829],"iteration":67,"passed_time":0.1192775774,"remaining_time":1.634804443},
{"learn":[1748032.084],"iteration":68,"passed_time":0.1201727202,"remaining_time":1.621460906},
{"learn":[1746913.746],"iteration":69,"passed_time":0.1209944901,"remaining_time":1.607498225},
{"learn":[1746388.412],"iteration":70,"passed_time":0.121899841,"remaining_time":1.594999328},
{"learn":[1745829.511],"iteration":71,"passed_time":0.1228408993,"remaining_time":1.583282702},
{"learn":[1745389.329],"iteration":72,"passed_time":0.1236947099,"remaining_time":1.570753371},
{"learn":[1744703.709],"iteration":73,"passed_time":0.124542479,"remaining_time":1.558463994},
{"learn":[1743782.143],"iteration":74,"passed_time":0.1254080393,"remaining_time":1.546699152},
{"learn":[1743049.491],"iteration":75,"passed_time":0.1263582224,"remaining_time":1.536249967},
{"learn":[1742361.752],"iteration":76,"passed_time":0.1273369047,"remaining_time":1.52638913},
{"learn":[1741851.466],"iteration":77,"passed_time":0.1282821712,"remaining_time":1.516361049},
{"learn":[1741272.854],"iteration":78,"passed_time":0.1291218989,"remaining_time":1.505332517},
{"learn":[1740436.979],"iteration":79,"passed_time":0.1299305857,"remaining_time":1.494201736},
{"learn":[1740414.645],"iteration":80,"passed_time":0.1305328197,"remaining_time":1.480983473},
{"learn":[1739782.247],"iteration":81,"passed_time":0.1314381706,"remaining_time":1.471466349},
{"learn":[1739189.094],"iteration":82,"passed_time":0.1322654403,"remaining_time":1.461294081},
{"learn":[1738769.39],"iteration":83,"passed_time":0.1332296229,"remaining_time":1.452837317},
{"learn":[1738110.321],"iteration":84,"passed_time":0.1340341432,"remaining_time":1.44283813},
{"learn":[1737347.497],"iteration":85,"passed_time":0.1348905371,"remaining_time":1.43360408},
{"learn":[1736079.47],"iteration":86,"passed_time":0.1356568084,"remaining_time":1.423616851},
{"learn":[1735452.401],"iteration":87,"passed_time":0.1364846614,"remaining_time":1.4144774},
{"learn":[1734828.54],"iteration":88,"passed_time":0.1374631353,"remaining_time":1.407066475},
{"learn":[1734285.423],"iteration":89,"passed_time":0.1384134017,"remaining_time":1.399513284},
{"learn":[1733537.414],"iteration":90,"passed_time":0.1392302133,"remaining_time":1.390772131},
{"learn":[1732988.624],"iteration":91,"passed_time":0.1401594803,"remaining_time":1.383313132},
{"learn":[1732398.816],"iteration":92,"passed_time":0.1410125409,"remaining_time":1.37525134},
{"learn":[1731791.85],"iteration":93,"passed_time":0.1418272693,"remaining_time":1.366973468},
{"learn":[1731412.421],"iteration":94,"passed_time":0.1426874131,"remaining_time":1.359285356},
{"learn":[1730875.836],"iteration":95,"passed_time":0.1436206382,"remaining_time":1.352427677},
{"learn":[1730111.239],"iteration":96,"passed_time":0.1445898624,"remaining_time":1.346027276},
{"learn":[1729339.693],"iteration":97,"passed_time":0.1455035881,"remaining_time":1.339226903},
{"learn":[1728175.038],"iteration":98,"passed_time":0.146274651,"remaining_time":1.331247076},
{"learn":[1727691.914],"iteration":99,"passed_time":0.1471384197,"remaining_time":1.324245777},
{"learn":[1727462.369],"iteration":100,"passed_time":0.1479127324,"remaining_time":1.316569767},
{"learn":[1726665.872],"iteration":101,"passed_time":0.1488246665,"remaining_time":1.310240691},
{"learn":[1726368.347],"iteration":102,"passed_time":0.1496898518,"remaining_time":1.30360968},
{"learn":[1725502.648],"iteration":103,"passed_time":0.150608619,"remaining_time":1.297551179},
{"learn":[1724749.551],"iteration":104,"passed_time":0.1513804735,"remaining_time":1.290338322},
{"learn":[1723688.869],"iteration":105,"passed_time":0.1522833245,"remaining_time":1.284351812},
{"learn":[1722991.149],"iteration":106,"passed_time":0.1531111358,"remaining_time":1.277834059},
{"learn":[1721708.339],"iteration":107,"passed_time":0.1540653604,"remaining_time":1.272465755},
{"learn":[1721022.412],"iteration":108,"passed_time":0.1549372122,"remaining_time":1.266505102},
{"learn":[1720474.23],"iteration":109,"passed_time":0.1559407272,"remaining_time":1.261702247},
{"learn":[1719819.807],"iteration":110,"passed_time":0.1567218731,"remaining_time":1.255186893},
{"learn":[1719212.119],"iteration":111,"passed_time":0.1575818502,"remaining_time":1.249398955},
{"learn":[1718537.633],"iteration":112,"passed_time":0.1584060366,"remaining_time":1.243417296},
{"learn":[1717706.689],"iteration":113,"passed_time":0.1592792634,"remaining_time":1.237907258},
{"learn":[1716739.651],"iteration":114,"passed_time":0.1601083663,"remaining_time":1.232138298},
{"learn":[1715997.058],"iteration":115,"passed_time":0.1609438858,"remaining_time":1.226503405},
{"learn":[1715465.002],"iteration":116,"passed_time":0.1617708638,"remaining_time":1.220886092},
{"learn":[1714804.252],"iteration":117,"passed_time":0.1626592152,"remaining_time":1.21580871},
{"learn":[1714381.26],"iteration":118,"passed_time":0.1635094842,"remaining_time":1.210519795},
{"learn":[1713712.066],"iteration":119,"passed_time":0.1643232126,"remaining_time":1.205036892},
{"learn":[1713206.117],"iteration":120,"passed_time":0.1651313161,"remaining_time":1.199590304},
{"learn":[1712566.366],"iteration":121,"passed_time":0.1659891266,"remaining_time":1.194577485},
{"learn":[1711922.825],"iteration":122,"passed_time":0.166889686,"remaining_time":1.189937029},
{"learn":[1711358.058],"iteration":123,"passed_time":0.1676927896,"remaining_time":1.184668417},
{"learn":[1710108.809],"iteration":124,"passed_time":0.1685972656,"remaining_time":1.180180859},
{"learn":[1709632.133],"iteration":125,"passed_time":0.1697477766,"remaining_time":1.1774568},
{"learn":[1708592.828],"iteration":126,"passed_time":0.1705661299,"remaining_time":1.172474263},
{"learn":[1708232.484],"iteration":127,"passed_time":0.1714905636,"remaining_time":1.168279464},
{"learn":[1707688.987],"iteration":128,"passed_time":0.1725310776,"remaining_time":1.164919136},
{"learn":[1707064],"iteration":129,"passed_time":0.173419054,"remaining_time":1.160573669},
{"learn":[1706625.461],"iteration":130,"passed_time":0.1743899031,"remaining_time":1.156830732},
{"learn":[1705907.87],"iteration":131,"passed_time":0.1752809628,"remaining_time":1.152605119},
{"learn":[1705094.266],"iteration":132,"passed_time":0.1761718141,"remaining_time":1.148428292},
{"learn":[1704581.609],"iteration":133,"passed_time":0.1770719568,"remaining_time":1.144360557},
{"learn":[1704154.289],"iteration":134,"passed_time":0.1778877268,"remaining_time":1.139799138},
{"learn":[1703239.77],"iteration":135,"passed_time":0.1787290377,"remaining_time":1.135455063},
{"learn":[1702413.921],"iteration":136,"passed_time":0.179596598,"remaining_time":1.131327475},
{"learn":[1701795.944],"iteration":137,"passed_time":0.1805105737,"remaining_time":1.127537062},
{"learn":[1701101.5],"iteration":138,"passed_time":0.181439799,"remaining_time":1.123882496},
{"learn":[1700465.713],"iteration":139,"passed_time":0.1822501524,"remaining_time":1.11953665},
{"learn":[1699944.81],"iteration":140,"passed_time":0.1831092546,"remaining_time":1.115537941},
{"learn":[1699450.995],"iteration":141,"passed_time":0.1839662318,"remaining_time":1.111570612},
{"learn":[1698662.94],"iteration":142,"passed_time":0.1848534998,"remaining_time":1.107828317},
{"learn":[1698306.926],"iteration":143,"passed_time":0.1857105187,"remaining_time":1.103945861},
{"learn":[1697730.086],"iteration":144,"passed_time":0.1865989534,"remaining_time":1.10029038},
{"learn":[1697488.458],"iteration":145,"passed_time":0.1876325509,"remaining_time":1.097521907},
{"learn":[1696707.515],"iteration":146,"passed_time":0.1885336519,"remaining_time":1.094008198},
{"learn":[1696146.8],"iteration":147,"passed_time":0.1895314587,"remaining_time":1.091086506},
{"learn":[1695499.802],"iteration":148,"passed_time":0.190412602,"remaining_time":1.087524324},
{"learn":[1694969.201],"iteration":149,"passed_time":0.1912949952,"remaining_time":1.084004973},
{"learn":[1694235.34],"iteration":150,"passed_time":0.192126223,"remaining_time":1.08023287},
{"learn":[1693744.593],"iteration":151,"passed_time":0.1930195743,"remaining_time":1.076846046},
{"learn":[1693134.93],"iteration":152,"passed_time":0.1938576353,"remaining_time":1.073185733},
{"learn":[1692238.589],"iteration":153,"passed_time":0.1947417368,"remaining_time":1.069814996},
{"learn":[1691552.977],"iteration":154,"passed_time":0.1956614207,"remaining_time":1.066670326},
{"learn":[1691186.768],"iteration":155,"passed_time":0.1964587745,"remaining_time":1.062892344},
{"learn":[1690819.616],"iteration":156,"passed_time":0.1973229182,"remaining_time":1.059510955},
{"learn":[1690427.816],"iteration":157,"passed_time":0.1981275634,"remaining_time":1.055844357},
{"learn":[1689846.826],"iteration":158,"passed_time":0.1991059124,"remaining_time":1.05313253},
{"learn":[1689143.267],"iteration":159,"passed_time":0.2000646786,"remaining_time":1.050339562},
{"learn":[1688597.486],"iteration":160,"passed_time":0.2009767793,"remaining_time":1.047326198},
{"learn":[1687814.523],"iteration":161,"passed_time":0.2020162933,"remaining_time":1.044997863},
{"learn":[1686655.785],"iteration":162,"passed_time":0.2029010615,"remaining_time":1.041890727},
{"learn":[1686059.542],"iteration":163,"passed_time":0.2038802854,"remaining_time":1.039292187},
{"learn":[1685330.085],"iteration":164,"passed_time":0.2047910528,"remaining_time":1.036366843},
{"learn":[1684677.988],"iteration":165,"passed_time":0.2057765683,"remaining_time":1.033841313},
{"learn":[1683949.674],"iteration":166,"passed_time":0.2065784636,"remaining_time":1.030418325},
{"learn":[1683350.454],"iteration":167,"passed_time":0.2074506488,"remaining_time":1.027374642},
{"learn":[1682652.656],"iteration":168,"passed_time":0.2083135425,"remaining_time":1.024310969},
{"learn":[1682083.843],"iteration":169,"passed_time":0.209183436,"remaining_time":1.021307364},
{"learn":[1681251.722],"iteration":170,"passed_time":0.2101175778,"remaining_time":1.018640187},
{"learn":[1680747.197],"iteration":171,"passed_time":0.2110073042,"remaining_time":1.015779348},
{"learn":[1680468.123],"iteration":172,"passed_time":0.2118664897,"remaining_time":1.0127953},
{"learn":[1680029.364],"iteration":173,"passed_time":0.2126577603,"remaining_time":1.009513276},
{"learn":[1679396.37],"iteration":174,"passed_time":0.2138424788,"remaining_time":1.008114543},
{"learn":[1678878.285],"iteration":175,"passed_time":0.2146422075,"remaining_time":1.00491579},
{"learn":[1678480.308],"iteration":176,"passed_time":0.2155831825,"remaining_time":1.002400899},
{"learn":[1678124.636],"iteration":177,"passed_time":0.2164253684,"remaining_time":0.9994474878},
{"learn":[1677373.602],"iteration":178,"passed_time":0.2171890564,"remaining_time":0.9961576275},
{"learn":[1676911.887],"iteration":179,"passed_time":0.2180598249,"remaining_time":0.9933836469},
{"learn":[1676424.866],"iteration":180,"passed_time":0.2190452987,"remaining_time":0.9911497218},
{"learn":[1675903.275],"iteration":181,"passed_time":0.2200583968,"remaining_time":0.9890536734},
{"learn":[1675390.586],"iteration":182,"passed_time":0.2209323318,"remaining_time":0.9863481701},
{"learn":[1674646.535],"iteration":183,"passed_time":0.2219249304,"remaining_time":0.984188822},
{"learn":[1674053.14],"iteration":184,"passed_time":0.2229542364,"remaining_time":0.9822037982},
{"learn":[1673486.937],"iteration":185,"passed_time":0.2237704647,"remaining_time":0.9792965498},
{"learn":[1672734.274],"iteration":186,"passed_time":0.2247573134,"remaining_time":0.9771534536},
{"learn":[1672291.322],"iteration":187,"passed_time":0.2255935829,"remaining_time":0.9743722834},
{"learn":[1671813.141],"iteration":188,"passed_time":0.2264300606,"remaining_time":0.9716125881},
{"learn":[1671202.889],"iteration":189,"passed_time":0.2274687413,"remaining_time":0.9697351604},
{"learn":[1670693.457],"iteration":190,"passed_time":0.2283514262,"remaining_time":0.9672057789},
{"learn":[1669964.059],"iteration":191,"passed_time":0.2291899039,"remaining_time":0.9645075121},
{"learn":[1669180.905],"iteration":192,"passed_time":0.2300960881,"remaining_time":0.9621116223},
{"learn":[1668629.833],"iteration":193,"passed_time":0.2309844395,"remaining_time":0.9596570011},
{"learn":[1668060.534],"iteration":194,"passed_time":0.2318409584,"remaining_time":0.9570870332},
{"learn":[1667529.985],"iteration":195,"passed_time":0.2328739726,"remaining_time":0.9552585405},
{"learn":[1667069.235],"iteration":196,"passed_time":0.2338528632,"remaining_time":0.9532175083},
{"learn":[1666442.098],"iteration":197,"passed_time":0.2347305065,"remaining_time":0.9507771021},
{"learn":[1665896.221],"iteration":198,"passed_time":0.2355597344,"remaining_time":0.9481575241},
{"learn":[1665416.242],"iteration":199,"passed_time":0.2365126258,"remaining_time":0.9460505031},
{"learn":[1664598.594],"iteration":200,"passed_time":0.2374114769,"remaining_time":0.9437401493},
{"learn":[1663881.646],"iteration":201,"passed_time":0.2383854093,"remaining_time":0.9417403793},
{"learn":[1663443.595],"iteration":202,"passed_time":0.2391828464,"remaining_time":0.9390577763},
{"learn":[1663040.056],"iteration":203,"passed_time":0.2400076578,"remaining_time":0.9365004687},
{"learn":[1662348.834],"iteration":204,"passed_time":0.2408008034,"remaining_time":0.9338372619},
{"learn":[1661861.628],"iteration":205,"passed_time":0.2417577363,"remaining_time":0.9318235077},
{"learn":[1661212.3],"iteration":206,"passed_time":0.2426851699,"remaining_time":0.9297069553},
{"learn":[1660739.913],"iteration":207,"passed_time":0.2437517666,"remaining_time":0.9281317265},
{"learn":[1660202.841],"iteration":208,"passed_time":0.2446052438,"remaining_time":0.9257547746},
{"learn":[1659399.484],"iteration":209,"passed_time":0.2455155946,"remaining_time":0.9236062846},
{"learn":[1658945.373],"iteration":210,"passed_time":0.2464336952,"remaining_time":0.9214985096},
{"learn":[1658363.812],"iteration":211,"passed_time":0.2473859199,"remaining_time":0.9195287966},
{"learn":[1657794.944],"iteration":212,"passed_time":0.2483325614,"remaining_time":0.9175480085},
{"learn":[1657342.813],"iteration":213,"passed_time":0.2493785752,"remaining_time":0.9159418697},
{"learn":[1656711.781],"iteration":214,"passed_time":0.2502323858,"remaining_time":0.9136391762},
{"learn":[1656372.894],"iteration":215,"passed_time":0.2510851132,"remaining_time":0.9113459663},
{"learn":[1655992.648],"iteration":216,"passed_time":0.2519770061,"remaining_time":0.9092073538},
{"learn":[1655540.558],"iteration":217,"passed_time":0.2528381915,"remaining_time":0.9069700265},
{"learn":[1655059.175],"iteration":218,"passed_time":0.2537680001,"remaining_time":0.9049899913},
{"learn":[1654614.679],"iteration":219,"passed_time":0.2547324328,"remaining_time":0.9031422618},
{"learn":[1654263.318],"iteration":220,"passed_time":0.2556247841,"remaining_time":0.901048447},
{"learn":[1653720.183],"iteration":221,"passed_time":0.2564202213,"remaining_time":0.8986258204},
{"learn":[1653219.431],"iteration":222,"passed_time":0.2572411578,"remaining_time":0.8963066349},
{"learn":[1652634.768],"iteration":223,"passed_time":0.2581000516,"remaining_time":0.8941323215},
{"learn":[1652257.1],"iteration":224,"passed_time":0.2590061941,"remaining_time":0.8921324465},
{"learn":[1651815.709],"iteration":225,"passed_time":0.2598970038,"remaining_time":0.8900897386},
{"learn":[1651379.328],"iteration":226,"passed_time":0.2609369344,"remaining_time":0.8885649794},
{"learn":[1650837.766],"iteration":227,"passed_time":0.2617790371,"remaining_time":0.8863746342},
{"learn":[1650239.177],"iteration":228,"passed_time":0.2627610943,"remaining_time":0.884667265},
{"learn":[1649917.201],"iteration":229,"passed_time":0.2637631926,"remaining_time":0.883033297},
{"learn":[1649357.427],"iteration":230,"passed_time":0.264636836,"remaining_time":0.8809771728},
{"learn":[1648728.089],"iteration":231,"passed_time":0.2655924356,"remaining_time":0.8792025455},
{"learn":[1648237.641],"iteration":232,"passed_time":0.2665723679,"remaining_time":0.8775150479},
{"learn":[1647792.346],"iteration":233,"passed_time":0.2674007209,"remaining_time":0.8753374025},
{"learn":[1647226.876],"iteration":234,"passed_time":0.2682705727,"remaining_time":0.8733063325},
{"learn":[1646803.67],"iteration":235,"passed_time":0.2691613824,"remaining_time":0.8713529497},
{"learn":[1646126.882],"iteration":236,"passed_time":0.2700325259,"remaining_time":0.8693452204},
{"learn":[1645434.386],"iteration":237,"passed_time":0.2708472542,"remaining_time":0.8671664189},
{"learn":[1645024.282],"iteration":238,"passed_time":0.2717363555,"remaining_time":0.8652358434},
{"learn":[1644659.45],"iteration":239,"passed_time":0.2732800228,"remaining_time":0.8653867389},
{"learn":[1644264.412],"iteration":240,"passed_time":0.2741548745,"remaining_time":0.863417219},
{"learn":[1643642.215],"iteration":241,"passed_time":0.2751140157,"remaining_time":0.8617207599},
{"learn":[1643220.054],"iteration":242,"passed_time":0.2759612015,"remaining_time":0.859681603},
{"learn":[1642585.035],"iteration":243,"passed_time":0.2768889268,"remaining_time":0.8579017569},
{"learn":[1641745.704],"iteration":244,"passed_time":0.2777015719,"remaining_time":0.8557742317},
{"learn":[1641278.016],"iteration":245,"passed_time":0.2786297972,"remaining_time":0.8540116548},
{"learn":[1640761.806],"iteration":246,"passed_time":0.2795483561,"remaining_time":0.8522263649},
{"learn":[1640295.157],"iteration":247,"passed_time":0.2804404574,"remaining_time":0.8503678384},
{"learn":[1639673.211],"iteration":248,"passed_time":0.2812897264,"remaining_time":0.8483878897},
{"learn":[1639318.223],"iteration":249,"passed_time":0.2822632839,"remaining_time":0.8467898516},
{"learn":[1638688.824],"iteration":250,"passed_time":0.2831846344,"remaining_time":0.8450410005},
{"learn":[1638274.823],"iteration":251,"passed_time":0.2840207371,"remaining_time":0.84304568},
{"learn":[1637718.245],"iteration":252,"passed_time":0.2850105858,"remaining_time":0.8415134687},
{"learn":[1637043.802],"iteration":253,"passed_time":0.2860393918,"remaining_time":0.8400999459},
{"learn":[1636468.909],"iteration":254,"passed_time":0.2869208683,"remaining_time":0.8382590074},
{"learn":[1636066.066],"iteration":255,"passed_time":0.2877741373,"remaining_time":0.8363435865},
{"learn":[1635503.483],"iteration":256,"passed_time":0.2887116957,"remaining_time":0.8346801163},
{"learn":[1634877.063],"iteration":257,"passed_time":0.2895601314,"remaining_time":0.8327659594},
{"learn":[1634258.615],"iteration":258,"passed_time":0.2905062313,"remaining_time":0.8311394493},
{"learn":[1633856.541],"iteration":259,"passed_time":0.2912981269,"remaining_time":0.8290792842},
{"learn":[1633465.035],"iteration":260,"passed_time":0.2921756452,"remaining_time":0.8272712713},
{"learn":[1632899.993],"iteration":261,"passed_time":0.2929852903,"remaining_time":0.8252791766},
{"learn":[1632334.243],"iteration":262,"passed_time":0.2938122267,"remaining_time":0.8233445288},
{"learn":[1631837.616],"iteration":263,"passed_time":0.2947281607,"remaining_time":0.8216663873},
{"learn":[1631316.744],"iteration":264,"passed_time":0.2956459696,"remaining_time":0.8199991986},
{"learn":[1630701.555],"iteration":265,"passed_time":0.29656932,"remaining_time":0.8183529357},
{"learn":[1630121.973],"iteration":266,"passed_time":0.2974427551,"remaining_time":0.8165750543},
{"learn":[1629612.311],"iteration":267,"passed_time":0.2983040655,"remaining_time":0.8147708059},
{"learn":[1629130.212],"iteration":268,"passed_time":0.2992024583,"remaining_time":0.8130743384},
{"learn":[1628564.955],"iteration":269,"passed_time":0.3001486831,"remaining_time":0.8115131063},
{"learn":[1628264.787],"iteration":270,"passed_time":0.3010386595,"remaining_time":0.8098051024},
{"learn":[1627967.98],"iteration":271,"passed_time":0.3018591793,"remaining_time":0.8079172152},
{"learn":[1627343.102],"iteration":272,"passed_time":0.3028424448,"remaining_time":0.8064705399},
{"learn":[1627051.804],"iteration":273,"passed_time":0.3037081301,"remaining_time":0.8047157025},
{"learn":[1626661.877],"iteration":274,"passed_time":0.3045573575,"remaining_time":0.8029239426},
{"learn":[1626247.101],"iteration":275,"passed_time":0.3054830829,"remaining_time":0.8013396813},
{"learn":[1625751.264],"iteration":276,"passed_time":0.3062922697,"remaining_time":0.7994559964},
{"learn":[1625226.595],"iteration":277,"passed_time":0.3073274505,"remaining_time":0.7981669758},
{"learn":[1624774.416],"iteration":278,"passed_time":0.3083046329,"remaining_time":0.7967298935},
{"learn":[1624054.472],"iteration":279,"passed_time":0.309263524,"remaining_time":0.7952490618},
{"learn":[1623558.986],"iteration":280,"passed_time":0.3103739528,"remaining_time":0.7941596871},
{"learn":[1623067.466],"iteration":281,"passed_time":0.3114838816,"remaining_time":0.7930688901},
{"learn":[1622489.232],"iteration":282,"passed_time":0.3123691498,"remaining_time":0.7914087646},
{"learn":[1622190.169],"iteration":283,"passed_time":0.3133443322,"remaining_time":0.7899807811},
{"learn":[1621554.327],"iteration":284,"passed_time":0.3143440972,"remaining_time":0.7886176474},
{"learn":[1621153.829],"iteration":285,"passed_time":0.3152726975,"remaining_time":0.7870793917},
{"learn":[1620499.275],"iteration":286,"passed_time":0.3162645045,"remaining_time":0.7857024101},
{"learn":[1620070.191],"iteration":287,"passed_time":0.3170783578,"remaining_time":0.7838881624},
{"learn":[1619458.898],"iteration":288,"passed_time":0.317900086,"remaining_time":0.7821002115},
{"learn":[1618931.762],"iteration":289,"passed_time":0.3188456025,"remaining_time":0.7806219923},
{"learn":[1618470.933],"iteration":290,"passed_time":0.3197191626,"remaining_time":0.7789721178},
{"learn":[1618012.374],"iteration":291,"passed_time":0.3205644318,"remaining_time":0.7772589647},
{"learn":[1617476.32],"iteration":292,"passed_time":0.3214136175,"remaining_time":0.7755611863},
{"learn":[1616787.039],"iteration":293,"passed_time":0.3223436761,"remaining_time":0.7740633855},
{"learn":[1616151.732],"iteration":294,"passed_time":0.3232620267,"remaining_time":0.7725414536},
{"learn":[1615569.053],"iteration":295,"passed_time":0.3241374201,"remaining_time":0.7709214315},
{"learn":[1615003.261],"iteration":296,"passed_time":0.3250374378,"remaining_time":0.7693647097},
{"learn":[1614583.279],"iteration":297,"passed_time":0.3259131645,"remaining_time":0.7677551728},
{"learn":[1613940.853],"iteration":298,"passed_time":0.326735976,"remaining_time":0.7660264854},
{"learn":[1613437.053],"iteration":299,"passed_time":0.3275625373,"remaining_time":0.764312587},
{"learn":[1612942.976],"iteration":300,"passed_time":0.32840189,"remaining_time":0.7626342894},
{"learn":[1612657.516],"iteration":301,"passed_time":0.3292597422,"remaining_time":0.7610043047},
{"learn":[1611981.243],"iteration":302,"passed_time":0.3300813036,"remaining_time":0.7592959361},
{"learn":[1611560.958],"iteration":303,"passed_time":0.3310644442,"remaining_time":0.7579633327},
{"learn":[1611063.039],"iteration":304,"passed_time":0.3318770059,"remaining_time":0.7562443249},
{"learn":[1610614.517],"iteration":305,"passed_time":0.3327687738,"remaining_time":0.7547108792},
{"learn":[1610204.635],"iteration":306,"passed_time":0.3336074182,"remaining_time":0.7530616964},
{"learn":[1609769.075],"iteration":307,"passed_time":0.3347471795,"remaining_time":0.7520943125},
{"learn":[1609352.823],"iteration":308,"passed_time":0.3357479862,"remaining_time":0.750815076},
{"learn":[1608765.073],"iteration":309,"passed_time":0.3367166272,"remaining_time":0.7494660411},
{"learn":[1608132.751],"iteration":310,"passed_time":0.3376911012,"remaining_time":0.7481323754},
{"learn":[1607617.895],"iteration":311,"passed_time":0.3386546173,"remaining_time":0.7467768483},
{"learn":[1607029.223],"iteration":312,"passed_time":0.3395525101,"remaining_time":0.7452797904},
{"learn":[1606472.308],"iteration":313,"passed_time":0.3403970709,"remaining_time":0.7436700339},
{"learn":[1605958.647],"iteration":314,"passed_time":0.341234132,"remaining_time":0.7420488267},
{"learn":[1605715.292],"iteration":315,"passed_time":0.3421503993,"remaining_time":0.7406040288},
{"learn":[1605376.993],"iteration":316,"passed_time":0.3430128763,"remaining_time":0.7390466705},
{"learn":[1605119.769],"iteration":317,"passed_time":0.3439706842,"remaining_time":0.737698134},
{"learn":[1604690.914],"iteration":318,"passed_time":0.3448234532,"remaining_time":0.7361278107},
{"learn":[1604258.435],"iteration":319,"passed_time":0.3457125129,"remaining_time":0.7346390899},
{"learn":[1603848.649],"iteration":320,"passed_time":0.3466443631,"remaining_time":0.7332446185},
{"learn":[1603414.669],"iteration":321,"passed_time":0.347675294,"remaining_time":0.7320616439},
{"learn":[1602781.27],"iteration":322,"passed_time":0.3484777727,"remaining_time":0.7304007805},
{"learn":[1602406.212],"iteration":323,"passed_time":0.3492557103,"remaining_time":0.7286940128},
{"learn":[1601988.669],"iteration":324,"passed_time":0.3500831883,"remaining_time":0.7270958526},
{"learn":[1601447.606],"iteration":325,"passed_time":0.3511265355,"remaining_time":0.7259487268},
{"learn":[1601065.703],"iteration":326,"passed_time":0.3519842211,"remaining_time":0.7244201247},
{"learn":[1600591.461],"iteration":327,"passed_time":0.3528066575,"remaining_time":0.7228233959},
{"learn":[1600076.481],"iteration":328,"passed_time":0.3538980035,"remaining_time":0.7217798187},
{"learn":[1599563.45],"iteration":329,"passed_time":0.3555349599,"remaining_time":0.7218437066},
{"learn":[1599076.404],"iteration":330,"passed_time":0.3564001453,"remaining_time":0.7203374537},
{"learn":[1598707.142],"iteration":331,"passed_time":0.3572793302,"remaining_time":0.7188632307},
{"learn":[1598172.836],"iteration":332,"passed_time":0.3581223495,"remaining_time":0.7173201414},
{"learn":[1597716.925],"iteration":333,"passed_time":0.3589869931,"remaining_time":0.7158243635},
{"learn":[1597262.646],"iteration":334,"passed_time":0.3599793417,"remaining_time":0.7145858575},
{"learn":[1596939.223],"iteration":335,"passed_time":0.3608744429,"remaining_time":0.7131566372},
{"learn":[1596365.807],"iteration":336,"passed_time":0.3617261286,"remaining_time":0.7116451729},
{"learn":[1595918.345],"iteration":337,"passed_time":0.3627180189,"remaining_time":0.7104122145},
{"learn":[1595368.542],"iteration":338,"passed_time":0.3636169116,"remaining_time":0.7089993469},
{"learn":[1595033.085],"iteration":339,"passed_time":0.3644389314,"remaining_time":0.7074402787},
{"learn":[1594652.928],"iteration":340,"passed_time":0.3654714873,"remaining_time":0.7062924051},
{"learn":[1594173.253],"iteration":341,"passed_time":0.3664342117,"remaining_time":0.7050108518},
{"learn":[1593667.659],"iteration":342,"passed_time":0.3678665486,"remaining_time":0.7046306777},
{"learn":[1593165.84],"iteration":343,"passed_time":0.3687004014,"remaining_time":0.7031030911},
{"learn":[1592668.203],"iteration":344,"passed_time":0.3695782114,"remaining_time":0.7016629811},
{"learn":[1592087.359],"iteration":345,"passed_time":0.3706610159,"remaining_time":0.7006135966},
{"learn":[1591726.853],"iteration":346,"passed_time":0.3715227847,"remaining_time":0.6991480646},
{"learn":[1591383.289],"iteration":347,"passed_time":0.3725691319,"remaining_time":0.6980318218},
{"learn":[1590972.508],"iteration":348,"passed_time":0.3734466502,"remaining_time":0.6966010581},
{"learn":[1590592.42],"iteration":349,"passed_time":0.3743140854,"remaining_time":0.6951547301},
{"learn":[1589957.895],"iteration":350,"passed_time":0.3751951037,"remaining_time":0.6937368156},
{"learn":[1589341.002],"iteration":351,"passed_time":0.3761169125,"remaining_time":0.6923970435},
{"learn":[1588867.638],"iteration":352,"passed_time":0.3770192218,"remaining_time":0.6910238995},
{"learn":[1588296.244],"iteration":353,"passed_time":0.3780466528,"remaining_time":0.689881745},
{"learn":[1587971.832],"iteration":354,"passed_time":0.3790032941,"remaining_time":0.6886116188},
{"learn":[1587354.518],"iteration":355,"passed_time":0.3798362302,"remaining_time":0.6871194727},
{"learn":[1586870.62],"iteration":356,"passed_time":0.3806761662,"remaining_time":0.6856436271},
{"learn":[1586471.356],"iteration":357,"passed_time":0.3815016859,"remaining_time":0.6841454815},
{"learn":[1586023.58],"iteration":358,"passed_time":0.3825969068,"remaining_time":0.6831326386},
{"learn":[1585570.051],"iteration":359,"passed_time":0.3834490925,"remaining_time":0.6816872755},
{"learn":[1585028.022],"iteration":360,"passed_time":0.3844793151,"remaining_time":0.6805603389},
{"learn":[1584446.514],"iteration":361,"passed_time":0.3853314174,"remaining_time":0.6791200119},
{"learn":[1583817.325],"iteration":362,"passed_time":0.3862644759,"remaining_time":0.6778249894},
{"learn":[1583219.495],"iteration":363,"passed_time":0.387187868,"remaining_time":0.6765150661},
{"learn":[1582701.213],"iteration":364,"passed_time":0.3881967579,"remaining_time":0.6753560034},
{"learn":[1582321.75],"iteration":365,"passed_time":0.3891383995,"remaining_time":0.6740812712},
{"learn":[1581990.671],"iteration":366,"passed_time":0.3900197094,"remaining_time":0.6727042944},
{"learn":[1581660.713],"iteration":367,"passed_time":0.390961476,"remaining_time":0.6714338392},
{"learn":[1581184.386],"iteration":368,"passed_time":0.3917845791,"remaining_time":0.6699622477},
{"learn":[1580732.39],"iteration":369,"passed_time":0.3926284733,"remaining_time":0.6685295627},
{"learn":[1580259.429],"iteration":370,"passed_time":0.3936051973,"remaining_time":0.6673252537},
{"learn":[1579891.265],"iteration":371,"passed_time":0.3944065927,"remaining_time":0.6658261833},
{"learn":[1579139.123],"iteration":372,"passed_time":0.3952380706,"remaining_time":0.6643814216},
{"learn":[1578827.342],"iteration":373,"passed_time":0.3960452574,"remaining_time":0.6628992811},
{"learn":[1578442.136],"iteration":374,"passed_time":0.3970164816,"remaining_time":0.661694136},
{"learn":[1577926.415],"iteration":375,"passed_time":0.3978739588,"remaining_time":0.6603014635},
{"learn":[1577553.606],"iteration":376,"passed_time":0.3988077673,"remaining_time":0.6590377693},
{"learn":[1577178.128],"iteration":377,"passed_time":0.399769575,"remaining_time":0.6578218933},
{"learn":[1576857.37],"iteration":378,"passed_time":0.400635052,"remaining_time":0.6564495179},
{"learn":[1576342.138],"iteration":379,"passed_time":0.4016674829,"remaining_time":0.6553522089},
{"learn":[1575815.06],"iteration":380,"passed_time":0.4025590008,"remaining_time":0.6540263032},
{"learn":[1575331.738],"iteration":381,"passed_time":0.4035372665,"remaining_time":0.6528430123},
{"learn":[1574788.221],"iteration":382,"passed_time":0.4043497865,"remaining_time":0.6513937814},
{"learn":[1574352.788],"iteration":383,"passed_time":0.4051638482,"remaining_time":0.6499503399},
{"learn":[1573928.799],"iteration":384,"passed_time":0.4059693268,"remaining_time":0.6484964571},
{"learn":[1573495.359],"iteration":385,"passed_time":0.406801013,"remaining_time":0.6470876217},
{"learn":[1572995.631],"iteration":386,"passed_time":0.4077209885,"remaining_time":0.6458216175},
{"learn":[1572311.63],"iteration":387,"passed_time":0.408719212,"remaining_time":0.6446808189},
{"learn":[1571853.406],"iteration":388,"passed_time":0.4096591453,"remaining_time":0.6434491974},
{"learn":[1571475.319],"iteration":389,"passed_time":0.4105955371,"remaining_time":0.6422135324},
{"learn":[1571031.478],"iteration":390,"passed_time":0.4114602641,"remaining_time":0.640867777},
{"learn":[1570702.56],"iteration":391,"passed_time":0.4123936559,"remaining_time":0.6396309765},
{"learn":[1570186.84],"iteration":392,"passed_time":0.4133007151,"remaining_time":0.6383550485},
{"learn":[1569701.043],"iteration":393,"passed_time":0.414208316,"remaining_time":0.6370818261},
{"learn":[1569183.753],"iteration":394,"passed_time":0.4151077921,"remaining_time":0.6357980106},
{"learn":[1568680.115],"iteration":395,"passed_time":0.4160824745,"remaining_time":0.6346308449},
{"learn":[1568303.947],"iteration":396,"passed_time":0.4171341132,"remaining_time":0.6335815371},
{"learn":[1567765.186],"iteration":397,"passed_time":0.4180434223,"remaining_time":0.6323169352},
{"learn":[1567287.778],"iteration":398,"passed_time":0.4189673561,"remaining_time":0.6310761428},
{"learn":[1566721.813],"iteration":399,"passed_time":0.419932997,"remaining_time":0.6298994956},
{"learn":[1566312.438],"iteration":400,"passed_time":0.4208008073,"remaining_time":0.6285777645},
{"learn":[1565985.017],"iteration":401,"passed_time":0.4216651593,"remaining_time":0.6272531474},
{"learn":[1565499.606],"iteration":402,"passed_time":0.4226630494,"remaining_time":0.6261286365},
{"learn":[1565202.953],"iteration":403,"passed_time":0.423520735,"remaining_time":0.6247979159},
{"learn":[1564729.277],"iteration":404,"passed_time":0.4243172971,"remaining_time":0.6233797328},
{"learn":[1564293.614],"iteration":405,"passed_time":0.4252236897,"remaining_time":0.6221252996},
{"learn":[1564005.466],"iteration":406,"passed_time":0.4260292932,"remaining_time":0.620725727},
{"learn":[1563577.722],"iteration":407,"passed_time":0.4269486021,"remaining_time":0.6194940501},
{"learn":[1563256.514],"iteration":408,"passed_time":0.4278029544,"remaining_time":0.6181700392},
{"learn":[1562843.105],"iteration":409,"passed_time":0.4286803477,"remaining_time":0.616881476},
{"learn":[1562511.332],"iteration":410,"passed_time":0.429683071,"remaining_time":0.6157745227},
{"learn":[1562004.139],"iteration":411,"passed_time":0.430648837,"remaining_time":0.6146153305},
{"learn":[1561645.856],"iteration":412,"passed_time":0.4315478548,"remaining_time":0.6133622052},
{"learn":[1561260.591],"iteration":413,"passed_time":0.4325362868,"remaining_time":0.6122373528},
{"learn":[1560657.729],"iteration":414,"passed_time":0.4333492235,"remaining_time":0.6108657729},
{"learn":[1560162.07],"iteration":415,"passed_time":0.434333989,"remaining_time":0.6097380999},
{"learn":[1559856.497],"iteration":416,"passed_time":0.4351876746,"remaining_time":0.6084278521},
{"learn":[1559413.076],"iteration":417,"passed_time":0.436115025,"remaining_time":0.6072223553},
{"learn":[1559097.516],"iteration":418,"passed_time":0.4370978738,"remaining_time":0.6060951425},
{"learn":[1558590.637],"iteration":419,"passed_time":0.4382840923,"remaining_time":0.6052494608},
{"learn":[1558119.869],"iteration":420,"passed_time":0.4391902765,"remaining_time":0.6040170311},
{"learn":[1557637.868],"iteration":421,"passed_time":0.4402545399,"remaining_time":0.6030026636},
{"learn":[1557276.289],"iteration":422,"passed_time":0.441088226,"remaining_time":0.6016735376},
{"learn":[1556747.605],"iteration":423,"passed_time":0.4419511614,"remaining_time":0.6003864834},
{"learn":[1556234.644],"iteration":424,"passed_time":0.4428528041,"remaining_time":0.5991537938},
{"learn":[1555759.567],"iteration":425,"passed_time":0.4437501135,"remaining_time":0.5979168197},
{"learn":[1555151.138],"iteration":426,"passed_time":0.4446077991,"remaining_time":0.5966282643},
{"learn":[1554626.268],"iteration":427,"passed_time":0.4455420242,"remaining_time":0.5954440137},
{"learn":[1554249.375],"iteration":428,"passed_time":0.4465976211,"remaining_time":0.5944224748},
{"learn":[1553782.854],"iteration":429,"passed_time":0.4474670563,"remaining_time":0.5931540049},
{"learn":[1553388.811],"iteration":430,"passed_time":0.4483988649,"remaining_time":0.5919697312},
{"learn":[1553169.224],"iteration":431,"passed_time":0.4493173405,"remaining_time":0.5907690958},
{"learn":[1552869.054],"iteration":432,"passed_time":0.4502811898,"remaining_time":0.5896291793},
{"learn":[1552474.16],"iteration":433,"passed_time":0.4511900823,"remaining_time":0.5884184023},
{"learn":[1551910.014],"iteration":434,"passed_time":0.4521826809,"remaining_time":0.587317735},
{"learn":[1551504.577],"iteration":435,"passed_time":0.4530783654,"remaining_time":0.5860921975},
{"learn":[1551074.861],"iteration":436,"passed_time":0.4539852163,"remaining_time":0.5848825556},
{"learn":[1550595.879],"iteration":437,"passed_time":0.4548509433,"remaining_time":0.58362153},
{"learn":[1549946.066],"iteration":438,"passed_time":0.4557440862,"remaining_time":0.5823973402},
{"learn":[1549429.727],"iteration":439,"passed_time":0.4566361041,"remaining_time":0.5811732234},
{"learn":[1548954.447],"iteration":440,"passed_time":0.457579579,"remaining_time":0.5800158383},
{"learn":[1548395.161],"iteration":441,"passed_time":0.4585500532,"remaining_time":0.5788935061},
{"learn":[1547745.175],"iteration":442,"passed_time":0.4593909892,"remaining_time":0.5776089864},
{"learn":[1547467.415],"iteration":443,"passed_time":0.4602695075,"remaining_time":0.5763735274},
{"learn":[1547068.971],"iteration":444,"passed_time":0.4612580645,"remaining_time":0.5752769119},
{"learn":[1546724.111],"iteration":445,"passed_time":0.4622421634,"remaining_time":0.5741752433},
{"learn":[1546256.044],"iteration":446,"passed_time":0.4632544281,"remaining_time":0.5731089457},
{"learn":[1545637.579],"iteration":447,"passed_time":0.4641309464,"remaining_time":0.5718756304},
{"learn":[1545299.175],"iteration":448,"passed_time":0.4649931735,"remaining_time":0.5706263666},
{"learn":[1544975.715],"iteration":449,"passed_time":0.4658426926,"remaining_time":0.5693632909},
{"learn":[1544532.834],"iteration":450,"passed_time":0.4668018754,"remaining_time":0.5682355423},
{"learn":[1544230.929],"iteration":451,"passed_time":0.4676619775,"remaining_time":0.5669884152},
{"learn":[1543794.293],"iteration":452,"passed_time":0.4685159965,"remaining_time":0.5657356514},
{"learn":[1543203.809],"iteration":453,"passed_time":0.4693260583,"remaining_time":0.5644317793},
{"learn":[1542876.046],"iteration":454,"passed_time":0.4702893243,"remaining_time":0.5633135863},
{"learn":[1542573.92],"iteration":455,"passed_time":0.4712319659,"remaining_time":0.5621714681},
{"learn":[1542046.784],"iteration":456,"passed_time":0.4720313196,"remaining_time":0.5608599706},
{"learn":[1541611.554],"iteration":457,"passed_time":0.4730541258,"remaining_time":0.5598151445},
{"learn":[1541167.78],"iteration":458,"passed_time":0.4740067671,"remaining_time":0.5586877146},
{"learn":[1540744.655],"iteration":459,"passed_time":0.4748404533,"remaining_time":0.5574214016},
{"learn":[1540150.117],"iteration":460,"passed_time":0.4757805949,"remaining_time":0.5562814331},
{"learn":[1539649.416],"iteration":461,"passed_time":0.4767234032,"remaining_time":0.5551454349},
{"learn":[1539247.268],"iteration":462,"passed_time":0.4776738362,"remaining_time":0.5540191146},
{"learn":[1539072.859],"iteration":463,"passed_time":0.4785686458,"remaining_time":0.5528292977},
{"learn":[1538596.47],"iteration":464,"passed_time":0.4802057272,"remaining_time":0.5524947614},
{"learn":[1538289.214],"iteration":465,"passed_time":0.4810712042,"remaining_time":0.5512704357},
{"learn":[1537867.147],"iteration":466,"passed_time":0.4819179733,"remaining_time":0.550026295},
{"learn":[1537395.181],"iteration":467,"passed_time":0.4827220353,"remaining_time":0.5487353051},
{"learn":[1536941.182],"iteration":468,"passed_time":0.4836310528,"remaining_time":0.5475652218},
{"learn":[1536445.226],"iteration":469,"passed_time":0.4845764443,"remaining_time":0.546437267},
{"learn":[1535998.142],"iteration":470,"passed_time":0.4854091305,"remaining_time":0.5451835032},
{"learn":[1535692.296],"iteration":471,"passed_time":0.4862131924,"remaining_time":0.5438995034},
{"learn":[1535270.425],"iteration":472,"passed_time":0.4870402538,"remaining_time":0.542643158},
{"learn":[1534879.633],"iteration":473,"passed_time":0.4879711457,"remaining_time":0.5415038452},
{"learn":[1534430.61],"iteration":474,"passed_time":0.4888639136,"remaining_time":0.5403232729},
{"learn":[1533969.234],"iteration":475,"passed_time":0.4897619314,"remaining_time":0.5391496891},
{"learn":[1533450.605],"iteration":476,"passed_time":0.4906441579,"remaining_time":0.5379599467},
{"learn":[1533122.395],"iteration":477,"passed_time":0.4915306343,"remaining_time":0.536776132},
{"learn":[1532890.859],"iteration":478,"passed_time":0.492521483,"remaining_time":0.5357070827},
{"learn":[1532488.914],"iteration":479,"passed_time":0.4934604997,"remaining_time":0.534582208},
{"learn":[1532214.021],"iteration":480,"passed_time":0.4943747253,"remaining_time":0.5334313564},
{"learn":[1531361.299],"iteration":481,"passed_time":0.4953799486,"remaining_time":0.5323792809},
{"learn":[1531190.739],"iteration":482,"passed_time":0.4964019631,"remaining_time":0.5313453725},
{"learn":[1530836.412],"iteration":483,"passed_time":0.4972786064,"remaining_time":0.5301565308},
{"learn":[1530378.217],"iteration":484,"passed_time":0.4983526612,"remaining_time":0.529178599},
{"learn":[1529958.309],"iteration":485,"passed_time":0.4992425125,"remaining_time":0.5280054556},
{"learn":[1529569.966],"iteration":486,"passed_time":0.5001832375,"remaining_time":0.5268870654},
{"learn":[1529116.81],"iteration":487,"passed_time":0.5010472145,"remaining_time":0.5256888808},
{"learn":[1528651.178],"iteration":488,"passed_time":0.5018599846,"remaining_time":0.5244385524},
{"learn":[1528046.304],"iteration":489,"passed_time":0.5028173341,"remaining_time":0.5233404906},
{"learn":[1527619.514],"iteration":490,"passed_time":0.5036877276,"remaining_time":0.5221528582},
{"learn":[1527254.187],"iteration":491,"passed_time":0.5047220751,"remaining_time":0.5211358011},
{"learn":[1526767.647],"iteration":492,"passed_time":0.5055993018,"remaining_time":0.5199570913},
{"learn":[1526338.204],"iteration":493,"passed_time":0.5065266938,"remaining_time":0.5188309859},
{"learn":[1525973.422],"iteration":494,"passed_time":0.5074397112,"remaining_time":0.5176910185},
{"learn":[1525611.976],"iteration":495,"passed_time":0.5083115213,"remaining_time":0.5165100942},
{"learn":[1525165.76],"iteration":496,"passed_time":0.5091256247,"remaining_time":0.5152720105},
{"learn":[1524752.198],"iteration":497,"passed_time":0.5100237674,"remaining_time":0.5141203439},
{"learn":[1524390.015],"iteration":498,"passed_time":0.5108872861,"remaining_time":0.5129349306},
{"learn":[1523844.082],"iteration":499,"passed_time":0.5118478022,"remaining_time":0.5118478022},
{"learn":[1523374.752],"iteration":500,"passed_time":0.5127580697,"remaining_time":0.5107111313},
{"learn":[1523024.4],"iteration":501,"passed_time":0.5135645482,"remaining_time":0.5094724005},
{"learn":[1522662.176],"iteration":502,"passed_time":0.5145108147,"remaining_time":0.5083735088},
{"learn":[1522257.53],"iteration":503,"passed_time":0.5155825779,"remaining_time":0.5073987275},
{"learn":[1521926.778],"iteration":504,"passed_time":0.5164721792,"remaining_time":0.5062450074},
{"learn":[1521297.494],"iteration":505,"passed_time":0.5174177374,"remaining_time":0.505146961},
{"learn":[1520928.76],"iteration":506,"passed_time":0.5182510069,"remaining_time":0.5039403282},
{"learn":[1520423.504],"iteration":507,"passed_time":0.5193617274,"remaining_time":0.5030038777},
{"learn":[1520086.503],"iteration":508,"passed_time":0.5201852055,"remaining_time":0.5017896579},
{"learn":[1519806.089],"iteration":509,"passed_time":0.5209730179,"remaining_time":0.5005427034},
{"learn":[1519299.588],"iteration":510,"passed_time":0.5218018708,"remaining_time":0.4993368196},
{"learn":[1518978.054],"iteration":511,"passed_time":0.522735096,"remaining_time":0.4982318884},
{"learn":[1518679.164],"iteration":512,"passed_time":0.5236153642,"remaining_time":0.4970773536},
{"learn":[1518331.285],"iteration":513,"passed_time":0.5244850911,"remaining_time":0.4959139188},
{"learn":[1517785.312],"iteration":514,"passed_time":0.5253621095,"remaining_time":0.4947584914},
{"learn":[1517401.672],"iteration":515,"passed_time":0.5262180867,"remaining_time":0.4935844069},
{"learn":[1516988.834],"iteration":516,"passed_time":0.5271696864,"remaining_time":0.4925008869},
{"learn":[1516711.898],"iteration":517,"passed_time":0.5279851647,"remaining_time":0.491291215},
{"learn":[1516258.023],"iteration":518,"passed_time":0.5289077235,"remaining_time":0.4901823025},
{"learn":[1515795.248],"iteration":519,"passed_time":0.5298779893,"remaining_time":0.489118144},
{"learn":[1515389.517],"iteration":520,"passed_time":0.5306601769,"remaining_time":0.4878814294},
{"learn":[1514915.078],"iteration":521,"passed_time":0.5315114876,"remaining_time":0.486709753},
{"learn":[1514590.127],"iteration":522,"passed_time":0.532309258,"remaining_time":0.4854904705},
{"learn":[1514307.205],"iteration":523,"passed_time":0.5332474414,"remaining_time":0.4844003475},
{"learn":[1514019.474],"iteration":524,"passed_time":0.534064128,"remaining_time":0.4832008777},
{"learn":[1513790.766],"iteration":525,"passed_time":0.5348684816,"remaining_time":0.4819917496},
{"learn":[1513304.301],"iteration":526,"passed_time":0.5357778741,"remaining_time":0.4808784335},
{"learn":[1512924.209],"iteration":527,"passed_time":0.5365947273,"remaining_time":0.4796831654},
{"learn":[1512427.172],"iteration":528,"passed_time":0.5374894119,"remaining_time":0.4785586257},
{"learn":[1512065.724],"iteration":529,"passed_time":0.5383886796,"remaining_time":0.4774390178},
{"learn":[1511682.83],"iteration":530,"passed_time":0.5393302379,"remaining_time":0.4763575924},
{"learn":[1511355.757],"iteration":531,"passed_time":0.5402620465,"remaining_time":0.4752681161},
{"learn":[1510935.691],"iteration":532,"passed_time":0.5411892718,"remaining_time":0.4741752156},
{"learn":[1510498.983],"iteration":533,"passed_time":0.5420564154,"remaining_time":0.4730305048},
{"learn":[1510141.642],"iteration":534,"passed_time":0.5428815185,"remaining_time":0.4718502917},
{"learn":[1509974.046],"iteration":535,"passed_time":0.5439489484,"remaining_time":0.4708811792},
{"learn":[1509666.853],"iteration":536,"passed_time":0.544965338,"remaining_time":0.4698676937},
{"learn":[1509130.201],"iteration":537,"passed_time":0.545781483,"remaining_time":0.46868224},
{"learn":[1508357.488],"iteration":538,"passed_time":0.5468365383,"remaining_time":0.4677024938},
{"learn":[1507881.197],"iteration":539,"passed_time":0.5477233063,"remaining_time":0.4665791128},
{"learn":[1507461.662],"iteration":540,"passed_time":0.5486306989,"remaining_time":0.465474105},
{"learn":[1506903.009],"iteration":541,"passed_time":0.5497129618,"remaining_time":0.464517595},
{"learn":[1506279.97],"iteration":542,"passed_time":0.5506151461,"remaining_time":0.463409064},
{"learn":[1505672.411],"iteration":543,"passed_time":0.5514671651,"remaining_time":0.4622592413},
{"learn":[1505256.665],"iteration":544,"passed_time":0.5524219314,"remaining_time":0.4611962913},
{"learn":[1504782.432],"iteration":545,"passed_time":0.553238868,"remaining_time":0.460019132},
{"learn":[1504445.393],"iteration":546,"passed_time":0.5541442606,"remaining_time":0.4589165448},
{"learn":[1503983.912],"iteration":547,"passed_time":0.5549859882,"remaining_time":0.4577621654},
{"learn":[1503643.862],"iteration":548,"passed_time":0.5559480042,"remaining_time":0.4567077412},
{"learn":[1503493.436],"iteration":549,"passed_time":0.5569302698,"remaining_time":0.4556702207},
{"learn":[1503214.318],"iteration":550,"passed_time":0.5578062048,"remaining_time":0.454546254},
{"learn":[1502753.811],"iteration":551,"passed_time":0.5587015977,"remaining_time":0.4534389778},
{"learn":[1502363.517],"iteration":552,"passed_time":0.5595568666,"remaining_time":0.452300035},
{"learn":[1501954.055],"iteration":553,"passed_time":0.560393136,"remaining_time":0.4511468207},
{"learn":[1501562.763],"iteration":554,"passed_time":0.5612960287,"remaining_time":0.4500481671},
{"learn":[1501148.459],"iteration":555,"passed_time":0.5623268346,"remaining_time":0.4490523643},
{"learn":[1500733.762],"iteration":556,"passed_time":0.5632975171,"remaining_time":0.4480086177},
{"learn":[1500348.312],"iteration":557,"passed_time":0.5641843685,"remaining_time":0.4468987292},
{"learn":[1499996.96],"iteration":558,"passed_time":0.5649999301,"remaining_time":0.4457333975},
{"learn":[1499691.445],"iteration":559,"passed_time":0.5658277831,"remaining_time":0.4445789725},
{"learn":[1499355.043],"iteration":560,"passed_time":0.5668233816,"remaining_time":0.4435569778},
{"learn":[1499080.095],"iteration":561,"passed_time":0.5676543179,"remaining_time":0.442406746},
{"learn":[1498815.034],"iteration":562,"passed_time":0.5684855874,"remaining_time":0.4412579071},
{"learn":[1498427.716],"iteration":563,"passed_time":0.569466978,"remaining_time":0.4402262454},
{"learn":[1497949.771],"iteration":564,"passed_time":0.5703960783,"remaining_time":0.4391545027},
{"learn":[1497579.052],"iteration":565,"passed_time":0.57127193,"remaining_time":0.4380424339},
{"learn":[1497081.907],"iteration":566,"passed_time":0.5722141966,"remaining_time":0.4369819173},
{"learn":[1496756.771],"iteration":567,"passed_time":0.5730567158,"remaining_time":0.4358459529},
{"learn":[1496356.286],"iteration":568,"passed_time":0.5740279817,"remaining_time":0.4348085415},
{"learn":[1495995.416],"iteration":569,"passed_time":0.5749350825,"remaining_time":0.433722957},
{"learn":[1495433.643],"iteration":570,"passed_time":0.5758292254,"remaining_time":0.4326282622},
{"learn":[1495171.711],"iteration":571,"passed_time":0.5768165325,"remaining_time":0.4316039789},
{"learn":[1494739.219],"iteration":572,"passed_time":0.577837297,"remaining_time":0.4306047571},
{"learn":[1494254.046],"iteration":573,"passed_time":0.5787674806,"remaining_time":0.4295382347},
{"learn":[1493871.284],"iteration":574,"passed_time":0.5796483738,"remaining_time":0.4284357546},
{"learn":[1493444.688],"iteration":575,"passed_time":0.5804890182,"remaining_time":0.4273044161},
{"learn":[1493142.004],"iteration":576,"passed_time":0.5815046995,"remaining_time":0.4263024053},
{"learn":[1492614.878],"iteration":577,"passed_time":0.5823740513,"remaining_time":0.4251935115},
{"learn":[1492346.799],"iteration":578,"passed_time":0.5833430672,"remaining_time":0.4241579124},
{"learn":[1491973.922],"iteration":579,"passed_time":0.584193378,"remaining_time":0.423036584},
{"learn":[1491634.101],"iteration":580,"passed_time":0.5852292254,"remaining_time":0.4220499922},
{"learn":[1491327.412],"iteration":581,"passed_time":0.5869018059,"remaining_time":0.421520541},
{"learn":[1491001.787],"iteration":582,"passed_time":0.5877787409,"remaining_time":0.4204180703},
{"learn":[1490371.266],"iteration":583,"passed_time":0.5888234631,"remaining_time":0.4194358915},
{"learn":[1489856.19],"iteration":584,"passed_time":0.5897027731,"remaining_time":0.4183361553},
{"learn":[1489332.406],"iteration":585,"passed_time":0.5905402508,"remaining_time":0.4172076175},
{"learn":[1488859.402],"iteration":586,"passed_time":0.5914616846,"remaining_time":0.416139141},
{"learn":[1488567.939],"iteration":587,"passed_time":0.5925028236,"remaining_time":0.4151550397},
{"learn":[1488280.991],"iteration":588,"passed_time":0.593341718,"remaining_time":0.4140296198},
{"learn":[1487758.943],"iteration":589,"passed_time":0.5941405717,"remaining_time":0.4128773464},
{"learn":[1487471.718],"iteration":590,"passed_time":0.5950993795,"remaining_time":0.4118369649},
{"learn":[1487235.828],"iteration":591,"passed_time":0.5959350656,"remaining_time":0.4107120047},
{"learn":[1486754.357],"iteration":592,"passed_time":0.5967835431,"remaining_time":0.4095967994},
{"learn":[1486266.414],"iteration":593,"passed_time":0.5976487284,"remaining_time":0.408493912},
{"learn":[1485685.372],"iteration":594,"passed_time":0.5986369521,"remaining_time":0.4074755724},
{"learn":[1485148.092],"iteration":595,"passed_time":0.5995534694,"remaining_time":0.4064087276},
{"learn":[1484824.133],"iteration":596,"passed_time":0.6003664478,"remaining_time":0.4052724932},
{"learn":[1484458.866],"iteration":597,"passed_time":0.6014127116,"remaining_time":0.404294164},
{"learn":[1484201.318],"iteration":598,"passed_time":0.6022484394,"remaining_time":0.4031746648},
{"learn":[1483833.337],"iteration":599,"passed_time":0.6031078749,"remaining_time":0.4020719166},
{"learn":[1483413.038],"iteration":600,"passed_time":0.6039131868,"remaining_time":0.4009340458},
{"learn":[1483076.098],"iteration":601,"passed_time":0.6047814553,"remaining_time":0.3998389024},
{"learn":[1482687.209],"iteration":602,"passed_time":0.6056406825,"remaining_time":0.3987385588},
{"learn":[1482195.08],"iteration":603,"passed_time":0.6066314478,"remaining_time":0.3977252539},
{"learn":[1481800.507],"iteration":604,"passed_time":0.607526924,"remaining_time":0.3966498099},
{"learn":[1481455.858],"iteration":605,"passed_time":0.6091614638,"remaining_time":0.3960554732},
{"learn":[1481170.123],"iteration":606,"passed_time":0.6102764342,"remaining_time":0.3951213157},
{"learn":[1480779.818],"iteration":607,"passed_time":0.6111901599,"remaining_time":0.3940568136},
{"learn":[1480425.141],"iteration":608,"passed_time":0.6121984247,"remaining_time":0.3930535042},
{"learn":[1480088.036],"iteration":609,"passed_time":0.6130249027,"remaining_time":0.3919339542},
{"learn":[1479669.764],"iteration":610,"passed_time":0.6138928797,"remaining_time":0.3908417843},
{"learn":[1479313.551],"iteration":611,"passed_time":0.6148658121,"remaining_time":0.3898168874},
{"learn":[1479027.462],"iteration":612,"passed_time":0.6158563691,"remaining_time":0.3888032869},
{"learn":[1478615.474],"iteration":613,"passed_time":0.6168132603,"remaining_time":0.3877685969},
{"learn":[1478301.411],"iteration":614,"passed_time":0.6176851121,"remaining_time":0.3866809238},
{"learn":[1477863.138],"iteration":615,"passed_time":0.6184674663,"remaining_time":0.3855381608},
{"learn":[1477530.694],"iteration":616,"passed_time":0.6195153551,"remaining_time":0.3845613955},
{"learn":[1477178.374],"iteration":617,"passed_time":0.6204859543,"remaining_time":0.3835366255},
{"learn":[1476867.975],"iteration":618,"passed_time":0.6214972607,"remaining_time":0.3825370862},
{"learn":[1476666.374],"iteration":619,"passed_time":0.6223764873,"remaining_time":0.3814565568},
{"learn":[1476299.006],"iteration":620,"passed_time":0.6232215065,"remaining_time":0.3803557987},
{"learn":[1476047.24],"iteration":621,"passed_time":0.6243154774,"remaining_time":0.3794071551},
{"learn":[1475670.735],"iteration":622,"passed_time":0.6251912041,"remaining_time":0.3783259775},
{"learn":[1475353.456],"iteration":623,"passed_time":0.6261937608,"remaining_time":0.3773218815},
{"learn":[1474939.671],"iteration":624,"passed_time":0.6272020673,"remaining_time":0.3763212404},
{"learn":[1474621.714],"iteration":625,"passed_time":0.6280347118,"remaining_time":0.3752156266},
{"learn":[1474291.064],"iteration":626,"passed_time":0.6290331436,"remaining_time":0.3742095097},
{"learn":[1473983.578],"iteration":627,"passed_time":0.6299886182,"remaining_time":0.3731779713},
{"learn":[1473438.779],"iteration":628,"passed_time":0.6308823028,"remaining_time":0.3721102295},
{"learn":[1473122.267],"iteration":629,"passed_time":0.6317775706,"remaining_time":0.37104397},
{"learn":[1472881.544],"iteration":630,"passed_time":0.6326970462,"remaining_time":0.3699924089},
{"learn":[1472599.11],"iteration":631,"passed_time":0.6335284407,"remaining_time":0.3688899781},
{"learn":[1472245.191],"iteration":632,"passed_time":0.6344480829,"remaining_time":0.3678395678},
{"learn":[1471847.178],"iteration":633,"passed_time":0.6353965994,"remaining_time":0.3668062387},
{"learn":[1471492.304],"iteration":634,"passed_time":0.6362859924,"remaining_time":0.3657391925},
{"learn":[1471208.898],"iteration":635,"passed_time":0.6371585108,"remaining_time":0.3646630471},
{"learn":[1470821.207],"iteration":636,"passed_time":0.6380537787,"remaining_time":0.363600505},
{"learn":[1470445.273],"iteration":637,"passed_time":0.6389797124,"remaining_time":0.362555887},
{"learn":[1470078.379],"iteration":638,"passed_time":0.6399362286,"remaining_time":0.3615289179},
{"learn":[1469761.671],"iteration":639,"passed_time":0.6407677482,"remaining_time":0.3604318583},
{"learn":[1469385.07],"iteration":640,"passed_time":0.6415706435,"remaining_time":0.359319596},
{"learn":[1468921.29],"iteration":641,"passed_time":0.6426038243,"remaining_time":0.358336712},
{"learn":[1468634.169],"iteration":642,"passed_time":0.6434487602,"remaining_time":0.3572491561},
{"learn":[1468338.98],"iteration":643,"passed_time":0.6443714023,"remaining_time":0.3562053093},
{"learn":[1468105.968],"iteration":644,"passed_time":0.6451465067,"remaining_time":0.3550806355},
{"learn":[1467899.768],"iteration":645,"passed_time":0.646050566,"remaining_time":0.3540277095},
{"learn":[1467399.103],"iteration":646,"passed_time":0.6470982464,"remaining_time":0.3530536028},
{"learn":[1467029.45],"iteration":647,"passed_time":0.6480257218,"remaining_time":0.3520139723},
{"learn":[1466620.366],"iteration":648,"passed_time":0.6489820713,"remaining_time":0.3509903036},
{"learn":[1466378.664],"iteration":649,"passed_time":0.649808466,"remaining_time":0.3498968663},
{"learn":[1465993.459],"iteration":650,"passed_time":0.6508323971,"remaining_time":0.3489101484},
{"learn":[1465389.22],"iteration":651,"passed_time":0.6517755387,"remaining_time":0.3478801955},
{"learn":[1465130.672],"iteration":652,"passed_time":0.6527303466,"remaining_time":0.3468567079},
{"learn":[1464307.174],"iteration":653,"passed_time":0.6535744909,"remaining_time":0.3457748835},
{"learn":[1463954.137],"iteration":654,"passed_time":0.654446426,"remaining_time":0.3447084229},
{"learn":[1463684.433],"iteration":655,"passed_time":0.6553576934,"remaining_time":0.3436631807},
{"learn":[1463465.035],"iteration":656,"passed_time":0.6562800439,"remaining_time":0.3426241325},
{"learn":[1463165.149],"iteration":657,"passed_time":0.6571193549,"remaining_time":0.3415422787},
{"learn":[1462880.951],"iteration":658,"passed_time":0.658004748,"remaining_time":0.3404850062},
{"learn":[1462466.428],"iteration":659,"passed_time":0.6588260178,"remaining_time":0.3393952213},
{"learn":[1462111.457],"iteration":660,"passed_time":0.6597752009,"remaining_time":0.3383718504},
{"learn":[1461754.969],"iteration":661,"passed_time":0.6606921349,"remaining_time":0.337332238},
{"learn":[1461511.653],"iteration":662,"passed_time":0.6617396487,"remaining_time":0.3363593689},
{"learn":[1461072.89],"iteration":663,"passed_time":0.6626714572,"remaining_time":0.3353277253},
{"learn":[1460803.865],"iteration":664,"passed_time":0.6635453506,"remaining_time":0.3342672067},
{"learn":[1460561.363],"iteration":665,"passed_time":0.6644635762,"remaining_time":0.3332294812},
{"learn":[1460293.135],"iteration":666,"passed_time":0.6653821351,"remaining_time":0.3321922804},
{"learn":[1460049.896],"iteration":667,"passed_time":0.6662510703,"remaining_time":0.3311307715},
{"learn":[1459820.929],"iteration":668,"passed_time":0.6671645877,"remaining_time":0.3300918962},
{"learn":[1459493.597],"iteration":669,"passed_time":0.6680881881,"remaining_time":0.3290583613},
{"learn":[1458938.998],"iteration":670,"passed_time":0.6689577483,"remaining_time":0.3279986575},
{"learn":[1458452.624],"iteration":671,"passed_time":0.6698283919,"remaining_time":0.3269400484},
{"learn":[1458039.788],"iteration":672,"passed_time":0.6706987437,"remaining_time":0.3258818562},
{"learn":[1457670.436],"iteration":673,"passed_time":0.6715309716,"remaining_time":0.3248057815},
{"learn":[1457055.505],"iteration":674,"passed_time":0.6723810323,"remaining_time":0.3237390155},
{"learn":[1456620.131],"iteration":675,"passed_time":0.6732535507,"remaining_time":0.3226836545},
{"learn":[1456268.62],"iteration":676,"passed_time":0.6740338633,"remaining_time":0.3215848417},
{"learn":[1455924.534],"iteration":677,"passed_time":0.6750392949,"remaining_time":0.3205938834},
{"learn":[1455590.013],"iteration":678,"passed_time":0.6760416016,"remaining_time":0.3196014052},
{"learn":[1455232.353],"iteration":679,"passed_time":0.6768717462,"remaining_time":0.3185278806},
{"learn":[1454855.353],"iteration":680,"passed_time":0.6778463036,"remaining_time":0.3175227178},
{"learn":[1454512.709],"iteration":681,"passed_time":0.6787968616,"remaining_time":0.3165064545},
{"learn":[1454194.617],"iteration":682,"passed_time":0.6796827964,"remaining_time":0.3154603901},
{"learn":[1453878.089],"iteration":683,"passed_time":0.6806583955,"remaining_time":0.3144562178},
{"learn":[1453305.087],"iteration":684,"passed_time":0.681526289,"remaining_time":0.3134026001},
{"learn":[1453024.842],"iteration":685,"passed_time":0.6823770997,"remaining_time":0.3123417045},
{"learn":[1452655.889],"iteration":686,"passed_time":0.6832432434,"remaining_time":0.3112884064},
{"learn":[1452341.286],"iteration":687,"passed_time":0.6841254699,"remaining_time":0.3102429457},
{"learn":[1452050.972],"iteration":688,"passed_time":0.6850226127,"remaining_time":0.3092046917},
{"learn":[1451834.146],"iteration":689,"passed_time":0.6859245054,"remaining_time":0.3081689807},
{"learn":[1451668.806],"iteration":690,"passed_time":0.6867374004,"remaining_time":0.3070938592},
{"learn":[1451354.304],"iteration":691,"passed_time":0.6876220436,"remaining_time":0.3060514298},
{"learn":[1451040.764],"iteration":692,"passed_time":0.6885147282,"remaining_time":0.3050130181},
{"learn":[1450544.3],"iteration":693,"passed_time":0.6894524532,"remaining_time":0.3039948857},
{"learn":[1450196.539],"iteration":694,"passed_time":0.6902680982,"remaining_time":0.30292341},
{"learn":[1449912.961],"iteration":695,"passed_time":0.6911362418,"remaining_time":0.3018755998},
{"learn":[1449416.955],"iteration":696,"passed_time":0.6921774224,"remaining_time":0.300903528},
{"learn":[1448826.575],"iteration":697,"passed_time":0.6929864842,"remaining_time":0.2998308284},
{"learn":[1448303.405],"iteration":698,"passed_time":0.6938735856,"remaining_time":0.2987924882},
{"learn":[1447854.801],"iteration":699,"passed_time":0.6948404349,"remaining_time":0.2977887578},
{"learn":[1447353.524],"iteration":700,"passed_time":0.6956414969,"remaining_time":0.2967144188},
{"learn":[1446928.465],"iteration":701,"passed_time":0.6966614281,"remaining_time":0.2957337686},
{"learn":[1446537.987],"iteration":702,"passed_time":0.6976236525,"remaining_time":0.294728627},
{"learn":[1446101.736],"iteration":703,"passed_time":0.6985254619,"remaining_time":0.2936982056},
{"learn":[1445617.819],"iteration":704,"passed_time":0.6994932695,"remaining_time":0.2926957652},
{"learn":[1445129.073],"iteration":705,"passed_time":0.7003272056,"remaining_time":0.2916376749},
{"learn":[1444689.857],"iteration":706,"passed_time":0.7011568502,"remaining_time":0.2905784401},
{"learn":[1444423.689],"iteration":707,"passed_time":0.701992078,"remaining_time":0.2895221565},
{"learn":[1444108.36],"iteration":708,"passed_time":0.7028271808,"remaining_time":0.2884664452},
{"learn":[1443878.389],"iteration":709,"passed_time":0.7037214487,"remaining_time":0.2874355213},
{"learn":[1443404.223],"iteration":710,"passed_time":0.7046837981,"remaining_time":0.2864326549},
{"learn":[1443125.191],"iteration":711,"passed_time":0.7055371504,"remaining_time":0.2853858136},
{"learn":[1442779.198],"iteration":712,"passed_time":0.7064137104,"remaining_time":0.2843488568},
{"learn":[1442320.042],"iteration":713,"passed_time":0.707280479,"remaining_time":0.2833084272},
{"learn":[1442033.561],"iteration":714,"passed_time":0.7081758302,"remaining_time":0.2822798764},
{"learn":[1441602.147],"iteration":715,"passed_time":0.7090704314,"remaining_time":0.2812514002},
{"learn":[1441281.37],"iteration":716,"passed_time":0.7099534079,"remaining_time":0.2802187091},
{"learn":[1441014.778],"iteration":717,"passed_time":0.7108877581,"remaining_time":0.2792066125},
{"learn":[1440660.605],"iteration":718,"passed_time":0.7117266108,"remaining_time":0.2781574098},
{"learn":[1440377.563],"iteration":719,"passed_time":0.7126076707,"remaining_time":0.2771252053},
{"learn":[1440070.966],"iteration":720,"passed_time":0.7135728533,"remaining_time":0.2761259724},
{"learn":[1439697.006],"iteration":721,"passed_time":0.7145784099,"remaining_time":0.2751423794},
{"learn":[1439347.717],"iteration":722,"passed_time":0.7154388453,"remaining_time":0.2741031261},
{"learn":[1439012.313],"iteration":723,"passed_time":0.7162846145,"remaining_time":0.2730587757},
{"learn":[1438658.563],"iteration":724,"passed_time":0.7172966709,"remaining_time":0.2720780476},
{"learn":[1438222.23],"iteration":725,"passed_time":0.7181690644,"remaining_time":0.2710445229},
{"learn":[1437744.833],"iteration":726,"passed_time":0.719010792,"remaining_time":0.269999926},
{"learn":[1437321.407],"iteration":727,"passed_time":0.7198956435,"remaining_time":0.2689719987},
{"learn":[1437054.906],"iteration":728,"passed_time":0.720777245,"remaining_time":0.2679432557},
{"learn":[1436585.079],"iteration":729,"passed_time":0.7223141625,"remaining_time":0.267157293},
{"learn":[1436340.837],"iteration":730,"passed_time":0.7231974306,"remaining_time":0.2661287399},
{"learn":[1436125.406],"iteration":731,"passed_time":0.7240709907,"remaining_time":0.2650970294},
{"learn":[1435669.596],"iteration":732,"passed_time":0.72491176,"remaining_time":0.2640538062},
{"learn":[1435434.289],"iteration":733,"passed_time":0.7258062779,"remaining_time":0.263030613},
{"learn":[1435063.483],"iteration":734,"passed_time":0.7266533804,"remaining_time":0.2619906746},
{"learn":[1434854.517],"iteration":735,"passed_time":0.7275753559,"remaining_time":0.2609781168},
{"learn":[1434522.26],"iteration":736,"passed_time":0.7285649545,"remaining_time":0.2599899363},
{"learn":[1434205.748],"iteration":737,"passed_time":0.7294485144,"remaining_time":0.2589641067},
{"learn":[1433797.519],"iteration":738,"passed_time":0.730351407,"remaining_time":0.2579454902},
{"learn":[1433515.097],"iteration":739,"passed_time":0.7311545523,"remaining_time":0.25689214},
{"learn":[1433092.47],"iteration":740,"passed_time":0.7321173184,"remaining_time":0.255895257},
{"learn":[1432576.592],"iteration":741,"passed_time":0.7329821287,"remaining_time":0.2548644059},
{"learn":[1432101.103],"iteration":742,"passed_time":0.7338646469,"remaining_time":0.2538401269},
{"learn":[1431707.174],"iteration":743,"passed_time":0.7347374154,"remaining_time":0.2528128741},
{"learn":[1431290.196],"iteration":744,"passed_time":0.7356095172,"remaining_time":0.2517858079},
{"learn":[1430832.461],"iteration":745,"passed_time":0.7366173237,"remaining_time":0.2508053622},
{"learn":[1430504.65],"iteration":746,"passed_time":0.7374278438,"remaining_time":0.2497580247},
{"learn":[1430155.619],"iteration":747,"passed_time":0.7383427778,"remaining_time":0.2487464973},
{"learn":[1429862.277],"iteration":748,"passed_time":0.7392805029,"remaining_time":0.2477428654},
{"learn":[1429440.333],"iteration":749,"passed_time":0.7402228945,"remaining_time":0.2467409648},
{"learn":[1429058.138],"iteration":750,"passed_time":0.7411699943,"remaining_time":0.2457407837},
{"learn":[1428715.245],"iteration":751,"passed_time":0.7420441793,"remaining_time":0.2447166974},
{"learn":[1428306.202],"iteration":752,"passed_time":0.7428822404,"remaining_time":0.2436811599},
{"learn":[1427964.853],"iteration":753,"passed_time":0.7436630113,"remaining_time":0.2426274546},
{"learn":[1427618.783],"iteration":754,"passed_time":0.7445688622,"remaining_time":0.2416150612},
{"learn":[1427348.054],"iteration":755,"passed_time":0.7453742991,"remaining_time":0.240570541},
{"learn":[1427079.884],"iteration":756,"passed_time":0.7461628198,"remaining_time":0.2395212222},
{"learn":[1426772.108],"iteration":757,"passed_time":0.7471113779,"remaining_time":0.2385236853},
{"learn":[1426573.031],"iteration":758,"passed_time":0.7480259369,"remaining_time":0.2375154819},
{"learn":[1426322.832],"iteration":759,"passed_time":0.748875706,"remaining_time":0.236487065},
{"learn":[1426067.175],"iteration":760,"passed_time":0.7496722681,"remaining_time":0.2354424075},
{"learn":[1425746.544],"iteration":761,"passed_time":0.7505594945,"remaining_time":0.2344267188},
{"learn":[1425488.865],"iteration":762,"passed_time":0.751469137,"remaining_time":0.2334183296},
{"learn":[1425176.168],"iteration":763,"passed_time":0.7522991566,"remaining_time":0.2323856033},
{"learn":[1424715.433],"iteration":764,"passed_time":0.7531503839,"remaining_time":0.2313599219},
{"learn":[1424422.036],"iteration":765,"passed_time":0.7540243607,"remaining_time":0.2303416454},
{"learn":[1424158.169],"iteration":766,"passed_time":0.7548950459,"remaining_time":0.2293227454},
{"learn":[1423891.039],"iteration":767,"passed_time":0.7558976442,"remaining_time":0.22834408},
{"learn":[1423628.781],"iteration":768,"passed_time":0.7567412051,"remaining_time":0.2273175792},
{"learn":[1423337.459],"iteration":769,"passed_time":0.7575875159,"remaining_time":0.2262923749},
{"learn":[1423026.41],"iteration":770,"passed_time":0.7584442848,"remaining_time":0.2252707409},
{"learn":[1422783.485],"iteration":771,"passed_time":0.7592333888,"remaining_time":0.2242295501},
{"learn":[1422474.117],"iteration":772,"passed_time":0.7600727831,"remaining_time":0.2232037798},
{"learn":[1422070.757],"iteration":773,"passed_time":0.7616626992,"remaining_time":0.2223976357},
{"learn":[1421793.352],"iteration":774,"passed_time":0.7625090933,"remaining_time":0.2213736077},
{"learn":[1421491.672],"iteration":775,"passed_time":0.7634378603,"remaining_time":0.2203738153},
{"learn":[1421177.972],"iteration":776,"passed_time":0.7643159203,"remaining_time":0.2193596528},
{"learn":[1420762.039],"iteration":777,"passed_time":0.76514094,"remaining_time":0.2183307052},
{"learn":[1420294.789],"iteration":778,"passed_time":0.766018625,"remaining_time":0.2173172222},
{"learn":[1419994.684],"iteration":779,"passed_time":0.7669631832,"remaining_time":0.2163229491},
{"learn":[1419759.438],"iteration":780,"passed_time":0.7679494486,"remaining_time":0.2153404984},
{"learn":[1419572.554],"iteration":781,"passed_time":0.768761427,"remaining_time":0.2143094515},
{"learn":[1419218.659],"iteration":782,"passed_time":0.7697003604,"remaining_time":0.2133141484},
{"learn":[1418821.528],"iteration":783,"passed_time":0.7705527544,"remaining_time":0.2122951466},
{"learn":[1418547.089],"iteration":784,"passed_time":0.7714141898,"remaining_time":0.2112790456},
{"learn":[1418187.689],"iteration":785,"passed_time":0.7723279988,"remaining_time":0.2102775976},
{"learn":[1417893.602],"iteration":786,"passed_time":0.7733348471,"remaining_time":0.2093015533},
{"learn":[1417707.655],"iteration":787,"passed_time":0.7741567002,"remaining_time":0.2082756605},
{"learn":[1417533.876],"iteration":788,"passed_time":0.7749983861,"remaining_time":0.2072555887},
{"learn":[1417130.572],"iteration":789,"passed_time":0.7758843626,"remaining_time":0.206247742},
{"learn":[1416835.259],"iteration":790,"passed_time":0.7767142155,"remaining_time":0.2052253743},
{"learn":[1416377.589],"iteration":791,"passed_time":0.7776149832,"remaining_time":0.2042221168},
{"learn":[1415895.035],"iteration":792,"passed_time":0.7785064595,"remaining_time":0.2032166925},
{"learn":[1415594.351],"iteration":793,"passed_time":0.7793622701,"remaining_time":0.2022023018},
{"learn":[1415127.281],"iteration":794,"passed_time":0.7802287054,"remaining_time":0.2011910498},
{"learn":[1414864.277],"iteration":795,"passed_time":0.781281844,"remaining_time":0.2002280103},
{"learn":[1414562.632],"iteration":796,"passed_time":0.7821417378,"remaining_time":0.1992155242},
{"learn":[1414213.888],"iteration":797,"passed_time":0.7832307505,"remaining_time":0.198261418},
{"learn":[1413979.559],"iteration":798,"passed_time":0.7840580202,"remaining_time":0.197241129},
{"learn":[1413798.666],"iteration":799,"passed_time":0.78506841,"remaining_time":0.1962671025},
{"learn":[1413560.674],"iteration":800,"passed_time":0.7858963046,"remaining_time":0.1952476462},
{"learn":[1413163.861],"iteration":801,"passed_time":0.7868059887,"remaining_time":0.1942488601},
{"learn":[1412836.374],"iteration":802,"passed_time":0.7878527942,"remaining_time":0.1932839358},
{"learn":[1412397.034],"iteration":803,"passed_time":0.7888325598,"remaining_time":0.1923024648},
{"learn":[1412105.883],"iteration":804,"passed_time":0.7896847872,"remaining_time":0.1912901037},
{"learn":[1411884.836],"iteration":805,"passed_time":0.7905694303,"remaining_time":0.1902859423},
{"learn":[1411412.37],"iteration":806,"passed_time":0.7915138635,"remaining_time":0.1892963763},
{"learn":[1411118.541],"iteration":807,"passed_time":0.7923491746,"remaining_time":0.188280992},
{"learn":[1410787.668],"iteration":808,"passed_time":0.7933371067,"remaining_time":0.1873020858},
{"learn":[1410423.517],"iteration":809,"passed_time":0.7941341272,"remaining_time":0.1862783755},
{"learn":[1410042.018],"iteration":810,"passed_time":0.7950316033,"remaining_time":0.185278635},
{"learn":[1409650.78],"iteration":811,"passed_time":0.7959103299,"remaining_time":0.1842748054},
{"learn":[1409449.229],"iteration":812,"passed_time":0.7967677654,"remaining_time":0.1832663864},
{"learn":[1409236.806],"iteration":813,"passed_time":0.7977773219,"remaining_time":0.1822930981},
{"learn":[1408771.752],"iteration":814,"passed_time":0.7986108414,"remaining_time":0.1812797616},
{"learn":[1408482.547],"iteration":815,"passed_time":0.7995204006,"remaining_time":0.1802840119},
{"learn":[1408197.002],"iteration":816,"passed_time":0.800355795,"remaining_time":0.1792718611},
{"learn":[1407891.295],"iteration":817,"passed_time":0.8011609819,"remaining_time":0.1782534214},
{"learn":[1407707.006],"iteration":818,"passed_time":0.8020814158,"remaining_time":0.1772609722},
{"learn":[1407431.457],"iteration":819,"passed_time":0.8029315182,"remaining_time":0.1762532601},
{"learn":[1407144.783],"iteration":820,"passed_time":0.8038842428,"remaining_time":0.1752683063},
{"learn":[1406890.755],"iteration":821,"passed_time":0.8048506755,"remaining_time":0.1742863993},
{"learn":[1406602.348],"iteration":822,"passed_time":0.8057060277,"remaining_time":0.1732806402},
{"learn":[1406316.506],"iteration":823,"passed_time":0.8067473333,"remaining_time":0.1723149644},
{"learn":[1405978.24],"iteration":824,"passed_time":0.807737682,"remaining_time":0.1713382962},
{"learn":[1405777.193],"iteration":825,"passed_time":0.8086517827,"remaining_time":0.1703455329},
{"learn":[1405425.98],"iteration":826,"passed_time":0.8094770524,"remaining_time":0.1693343773},
{"learn":[1405192.757],"iteration":827,"passed_time":0.8103889448,"remaining_time":0.1683416649},
{"learn":[1404823.49],"iteration":828,"passed_time":0.8112384639,"remaining_time":0.1673362815},
{"learn":[1404185.945],"iteration":829,"passed_time":0.8122046882,"remaining_time":0.1663551771},
{"learn":[1403933.746],"iteration":830,"passed_time":0.8130756233,"remaining_time":0.1653547297},
{"learn":[1403533.022],"iteration":831,"passed_time":0.8139314756,"remaining_time":0.164351548},
{"learn":[1403273.514],"iteration":832,"passed_time":0.8147224129,"remaining_time":0.1633357058},
{"learn":[1402894.788],"iteration":833,"passed_time":0.8155941397,"remaining_time":0.1623364834},
{"learn":[1402649.715],"iteration":834,"passed_time":0.8164189511,"remaining_time":0.1613282957},
{"learn":[1402365.584],"iteration":835,"passed_time":0.8172907196,"remaining_time":0.1603297584},
{"learn":[1402177.663],"iteration":836,"passed_time":0.8181068645,"remaining_time":0.1593206917},
{"learn":[1401798.862],"iteration":837,"passed_time":0.8189066766,"remaining_time":0.1583089279},
{"learn":[1401364],"iteration":838,"passed_time":0.819805486,"remaining_time":0.1573166666},
{"learn":[1401081.31],"iteration":839,"passed_time":0.8206769628,"remaining_time":0.1563194215},
{"learn":[1400790.672],"iteration":840,"passed_time":0.8215002326,"remaining_time":0.1553133615},
{"learn":[1400567.151],"iteration":841,"passed_time":0.822312211,"remaining_time":0.1543056168},
{"learn":[1400203.427],"iteration":842,"passed_time":0.8231952708,"remaining_time":0.1533115748},
{"learn":[1399866.354],"iteration":843,"passed_time":0.8240460399,"remaining_time":0.1523118273},
{"learn":[1399522.938],"iteration":844,"passed_time":0.8248996422,"remaining_time":0.1513129521},
{"learn":[1399162.079],"iteration":845,"passed_time":0.825759161,"remaining_time":0.1503154974},
{"learn":[1398673.056],"iteration":846,"passed_time":0.8265682228,"remaining_time":0.1493092539},
{"learn":[1398264.783],"iteration":847,"passed_time":0.8275688212,"remaining_time":0.1483378076},
{"learn":[1397889.317],"iteration":848,"passed_time":0.8284412146,"remaining_time":0.1473434905},
{"learn":[1397492.562],"iteration":849,"passed_time":0.8293297743,"remaining_time":0.1463523131},
{"learn":[1397182.371],"iteration":850,"passed_time":0.8302045844,"remaining_time":0.1453589695},
{"learn":[1396831.528],"iteration":851,"passed_time":0.831209141,"remaining_time":0.1443884423},
{"learn":[1396480.234],"iteration":852,"passed_time":0.8320710348,"remaining_time":0.1433932498},
{"learn":[1396250.388],"iteration":853,"passed_time":0.8329288453,"remaining_time":0.1423976714},
{"learn":[1395865.094],"iteration":854,"passed_time":0.8338011554,"remaining_time":0.1414048743},
{"learn":[1395576.216],"iteration":855,"passed_time":0.8346245085,"remaining_time":0.1404041229},
{"learn":[1395322.492],"iteration":856,"passed_time":0.8355991493,"remaining_time":0.1394290296},
{"learn":[1394997.897],"iteration":857,"passed_time":0.8364653345,"remaining_time":0.1384359878},
{"learn":[1394616.877],"iteration":858,"passed_time":0.8374155593,"remaining_time":0.1374570359},
{"learn":[1394215.853],"iteration":859,"passed_time":0.8383136187,"remaining_time":0.1364696589},
{"learn":[1393960.645],"iteration":860,"passed_time":0.8391768874,"remaining_time":0.1354768727},
{"learn":[1393584.509],"iteration":861,"passed_time":0.8400930714,"remaining_time":0.1344928583},
{"learn":[1393258.286],"iteration":862,"passed_time":0.84096059,"remaining_time":0.1335012756},
{"learn":[1392951.254],"iteration":863,"passed_time":0.8419021066,"remaining_time":0.1325216279},
{"learn":[1392700.948],"iteration":864,"passed_time":0.842826957,"remaining_time":0.1315394673},
{"learn":[1392343.683],"iteration":865,"passed_time":0.8436301856,"remaining_time":0.1305386199},
{"learn":[1391965.246],"iteration":866,"passed_time":0.8444973709,"remaining_time":0.1295480396},
{"learn":[1391551.027],"iteration":867,"passed_time":0.8453220573,"remaining_time":0.1285512806},
{"learn":[1391208.212],"iteration":868,"passed_time":0.8461206611,"remaining_time":0.1275509857},
{"learn":[1390916.042],"iteration":869,"passed_time":0.8469575555,"remaining_time":0.1265568761},
{"learn":[1390708.57],"iteration":870,"passed_time":0.8477794503,"remaining_time":0.125560906},
{"learn":[1390316.674],"iteration":871,"passed_time":0.8486313859,"remaining_time":0.1245697447},
{"learn":[1390123.86],"iteration":872,"passed_time":0.8495414034,"remaining_time":0.1235873519},
{"learn":[1389896.966],"iteration":873,"passed_time":0.8503867559,"remaining_time":0.1225958023},
{"learn":[1389728.763],"iteration":874,"passed_time":0.8511686101,"remaining_time":0.1215955157},
{"learn":[1389502.113],"iteration":875,"passed_time":0.8519884633,"remaining_time":0.1206011067},
{"learn":[1389186.622],"iteration":876,"passed_time":0.8528303159,"remaining_time":0.1196101811},
{"learn":[1388750.088],"iteration":877,"passed_time":0.8538893294,"remaining_time":0.1186497701},
{"learn":[1388441.262],"iteration":878,"passed_time":0.854720349,"remaining_time":0.11765775},
{"learn":[1387907.12],"iteration":879,"passed_time":0.8556228667,"remaining_time":0.1166758455},
{"learn":[1387702.46],"iteration":880,"passed_time":0.8564578444,"remaining_time":0.1156849983},
{"learn":[1387352.472],"iteration":881,"passed_time":0.8573709035,"remaining_time":0.1147049508},
{"learn":[1386942.211],"iteration":882,"passed_time":0.8581737571,"remaining_time":0.1137104525},
{"learn":[1386630.758],"iteration":883,"passed_time":0.8590017768,"remaining_time":0.1127196902},
{"learn":[1386268.649],"iteration":884,"passed_time":0.8598502959,"remaining_time":0.1117319594},
{"learn":[1386134.348],"iteration":885,"passed_time":0.8607076481,"remaining_time":0.1107456793},
{"learn":[1385756.776],"iteration":886,"passed_time":0.8617030799,"remaining_time":0.1097772808},
{"learn":[1385616.571],"iteration":887,"passed_time":0.8625339745,"remaining_time":0.1087880689},
{"learn":[1385321.517],"iteration":888,"passed_time":0.8634023264,"remaining_time":0.10780389},
{"learn":[1385042.397],"iteration":889,"passed_time":0.8644091329,"remaining_time":0.1068370838},
{"learn":[1384726.562],"iteration":890,"passed_time":0.8652745683,"remaining_time":0.1058528933},
{"learn":[1384418.601],"iteration":891,"passed_time":0.8662095434,"remaining_time":0.1048773887},
{"learn":[1384151.744],"iteration":892,"passed_time":0.8672053919,"remaining_time":0.1039092687},
{"learn":[1383658.387],"iteration":893,"passed_time":0.8681007848,"remaining_time":0.1029291758},
{"learn":[1383288.044],"iteration":894,"passed_time":0.869007594,"remaining_time":0.1019506116},
{"learn":[1382901.521],"iteration":895,"passed_time":0.8698943621,"remaining_time":0.1009698813},
{"learn":[1382368.851],"iteration":896,"passed_time":0.8707545892,"remaining_time":0.09998631291},
{"learn":[1382189.156],"iteration":897,"passed_time":0.8716055249,"remaining_time":0.09900196385},
{"learn":[1381948.975],"iteration":898,"passed_time":0.8724930846,"remaining_time":0.09802202619},
{"learn":[1381571.244],"iteration":899,"passed_time":0.8733607698,"remaining_time":0.09704008554},
{"learn":[1381367.702],"iteration":900,"passed_time":0.874333119,"remaining_time":0.09606989876},
{"learn":[1381125.352],"iteration":901,"passed_time":0.8754630889,"remaining_time":0.09511683228},
{"learn":[1380973.005],"iteration":902,"passed_time":0.8763558152,"remaining_time":0.09413788934},
{"learn":[1380661.584],"iteration":903,"passed_time":0.8772391667,"remaining_time":0.0931581416},
{"learn":[1380229.138],"iteration":904,"passed_time":0.8781356012,"remaining_time":0.09217998023},
{"learn":[1379888.482],"iteration":905,"passed_time":0.8791416578,"remaining_time":0.09121337288},
{"learn":[1379547.283],"iteration":906,"passed_time":0.8800177178,"remaining_time":0.09023334923},
{"learn":[1379292.037],"iteration":907,"passed_time":0.880948443,"remaining_time":0.08925909335},
{"learn":[1378913.609],"iteration":908,"passed_time":0.8819201672,"remaining_time":0.08828903764},
{"learn":[1378604.095],"iteration":909,"passed_time":0.88294114,"remaining_time":0.08732384901},
{"learn":[1378373.721],"iteration":910,"passed_time":0.8838328246,"remaining_time":0.08634590713},
{"learn":[1377977.641],"iteration":911,"passed_time":0.8846647608,"remaining_time":0.0853623892},
{"learn":[1377653.105],"iteration":912,"passed_time":0.8855498623,"remaining_time":0.08438426946},
{"learn":[1377389.298],"iteration":913,"passed_time":0.8865606271,"remaining_time":0.08341817717},
{"learn":[1377004.895],"iteration":914,"passed_time":0.8875487258,"remaining_time":0.08244988163},
{"learn":[1376765.4],"iteration":915,"passed_time":0.8883935783,"remaining_time":0.08146840675},
{"learn":[1376476.672],"iteration":916,"passed_time":0.8893006792,"remaining_time":0.08049286409},
{"learn":[1376078.924],"iteration":917,"passed_time":0.8902160299,"remaining_time":0.07951820746},
{"learn":[1375784.8],"iteration":918,"passed_time":0.8910465078,"remaining_time":0.07853619927},
{"learn":[1375585.97],"iteration":919,"passed_time":0.8920923133,"remaining_time":0.07757324463},
{"learn":[1375062.417],"iteration":920,"passed_time":0.8929349159,"remaining_time":0.07659268008},
{"learn":[1374757.469],"iteration":921,"passed_time":0.8939064317,"remaining_time":0.07562332069},
{"learn":[1374519.15],"iteration":922,"passed_time":0.895023902,"remaining_time":0.07466613267},
{"learn":[1374082.063],"iteration":923,"passed_time":0.8960654576,"remaining_time":0.07370235366},
{"learn":[1373712.603],"iteration":924,"passed_time":0.8969137684,"remaining_time":0.07272273798},
{"learn":[1373361.23],"iteration":925,"passed_time":0.897756121,"remaining_time":0.07174292975},
{"learn":[1372840.336],"iteration":926,"passed_time":0.8985793907,"remaining_time":0.07076191534},
{"learn":[1372626.813],"iteration":927,"passed_time":0.8994537425,"remaining_time":0.06978520416},
{"learn":[1372061.665],"iteration":928,"passed_time":0.9003856344,"remaining_time":0.06881311091},
{"learn":[1371717.015],"iteration":929,"passed_time":0.9013986074,"remaining_time":0.06784720701},
{"learn":[1371454.618],"iteration":930,"passed_time":0.9022440016,"remaining_time":0.06686878207},
{"learn":[1370836.807],"iteration":931,"passed_time":0.9031131868,"remaining_time":0.06589237844},
{"learn":[1370520.668],"iteration":932,"passed_time":0.9042796974,"remaining_time":0.06493755598},
{"learn":[1370208.977],"iteration":933,"passed_time":0.905112967,"remaining_time":0.06395873214},
{"learn":[1369934.886],"iteration":934,"passed_time":0.905974319,"remaining_time":0.06298217191},
{"learn":[1369549.418],"iteration":935,"passed_time":0.9068816699,"remaining_time":0.06200900307},
{"learn":[1369182.928],"iteration":936,"passed_time":0.9077303557,"remaining_time":0.06103203032},
{"learn":[1369003.064],"iteration":937,"passed_time":0.9085720833,"remaining_time":0.06005487118},
{"learn":[1368677.89],"iteration":938,"passed_time":0.9096006809,"remaining_time":0.05909014008},
{"learn":[1368371.05],"iteration":939,"passed_time":0.910588488,"remaining_time":0.05812266945},
{"learn":[1368072.662],"iteration":940,"passed_time":0.9114460485,"remaining_time":0.05714698923},
{"learn":[1367683.26],"iteration":941,"passed_time":0.9124171893,"remaining_time":0.05617855306},
{"learn":[1367398.463],"iteration":942,"passed_time":0.9133191237,"remaining_time":0.05520592794},
{"learn":[1367053.979],"iteration":943,"passed_time":0.9141646429,"remaining_time":0.05423010593},
{"learn":[1366798.357],"iteration":944,"passed_time":0.9150449944,"remaining_time":0.05325658698},
{"learn":[1366521.038],"iteration":945,"passed_time":0.9158522646,"remaining_time":0.05227909333},
{"learn":[1366252.93],"iteration":946,"passed_time":0.9168598212,"remaining_time":0.05131316845},
{"learn":[1365953.104],"iteration":947,"passed_time":0.9178651694,"remaining_time":0.05034703461},
{"learn":[1365581.757],"iteration":948,"passed_time":0.918732813,"remaining_time":0.04937341777},
{"learn":[1365209.556],"iteration":949,"passed_time":0.9196429971,"remaining_time":0.04840226301},
{"learn":[1364851.264],"iteration":950,"passed_time":0.9208109661,"remaining_time":0.04744451876},
{"learn":[1364602.513],"iteration":951,"passed_time":0.9215885287,"remaining_time":0.04646664851},
{"learn":[1364165.567],"iteration":952,"passed_time":0.9225637945,"remaining_time":0.04549894894},
{"learn":[1363899.507],"iteration":953,"passed_time":0.9235035195,"remaining_time":0.04452951981},
{"learn":[1363661.586],"iteration":954,"passed_time":0.9243956624,"remaining_time":0.04355791079},
{"learn":[1363409.4],"iteration":955,"passed_time":0.9253531369,"remaining_time":0.04258947492},
{"learn":[1362971.738],"iteration":956,"passed_time":0.9262190306,"remaining_time":0.04161694704},
{"learn":[1362633.96],"iteration":957,"passed_time":0.9272002128,"remaining_time":0.04064969618},
{"learn":[1362272.686],"iteration":958,"passed_time":0.928033399,"remaining_time":0.03967608901},
{"learn":[1362087.576],"iteration":959,"passed_time":0.9290134979,"remaining_time":0.03870889575},
{"learn":[1361686.417],"iteration":960,"passed_time":0.9298691001,"remaining_time":0.03773662321},
{"learn":[1361345.151],"iteration":961,"passed_time":0.9308277413,"remaining_time":0.03676866338},
{"learn":[1361059.789],"iteration":962,"passed_time":0.9316594275,"remaining_time":0.03579584509},
{"learn":[1360783.058],"iteration":963,"passed_time":0.9325042384,"remaining_time":0.03482380973},
{"learn":[1360165.073],"iteration":964,"passed_time":0.9333827567,"remaining_time":0.03385326061},
{"learn":[1359707.232],"iteration":965,"passed_time":0.9345345594,"remaining_time":0.03289252072},
{"learn":[1359472.773],"iteration":966,"passed_time":0.9353477877,"remaining_time":0.03191983143},
{"learn":[1359012.357],"iteration":967,"passed_time":0.936189182,"remaining_time":0.03094840271},
{"learn":[1358701.891],"iteration":968,"passed_time":0.9370299097,"remaining_time":0.02997722105},
{"learn":[1358490.751],"iteration":969,"passed_time":0.9381115476,"remaining_time":0.0290137592},
{"learn":[1358067.115],"iteration":970,"passed_time":0.9390944798,"remaining_time":0.02804710599},
{"learn":[1357824.091],"iteration":971,"passed_time":0.9399589568,"remaining_time":0.02707700699},
{"learn":[1357415.808],"iteration":972,"passed_time":0.9407813099,"remaining_time":0.02610595618},
{"learn":[1357106.584],"iteration":973,"passed_time":0.9417809083,"remaining_time":0.02513994211},
{"learn":[1356630.46],"iteration":974,"passed_time":0.9426840093,"remaining_time":0.02417138485},
{"learn":[1356436.447],"iteration":975,"passed_time":0.9436446921,"remaining_time":0.02320437767},
{"learn":[1356129.87],"iteration":976,"passed_time":0.9445840837,"remaining_time":0.02223688222},
{"learn":[1355804.669],"iteration":977,"passed_time":0.9454613104,"remaining_time":0.02126804584},
{"learn":[1355469.906],"iteration":978,"passed_time":0.9463018714,"remaining_time":0.02029861011},
{"learn":[1355267.523],"iteration":979,"passed_time":0.9470806007,"remaining_time":0.01932817552},
{"learn":[1354766.426],"iteration":980,"passed_time":0.9479201617,"remaining_time":0.01835930996},
{"learn":[1354545.47],"iteration":981,"passed_time":0.9490214657,"remaining_time":0.01739550548},
{"learn":[1354167.664],"iteration":982,"passed_time":0.9499795236,"remaining_time":0.01642894395},
{"learn":[1353879.967],"iteration":983,"passed_time":0.9508211678,"remaining_time":0.01546050679},
{"learn":[1353539.403],"iteration":984,"passed_time":0.9518793897,"remaining_time":0.01449562522},
{"learn":[1353298.475],"iteration":985,"passed_time":0.9528107399,"remaining_time":0.0135287529},
{"learn":[1352885.703],"iteration":986,"passed_time":0.9537842974,"remaining_time":0.01256250848},
{"learn":[1352484.292],"iteration":987,"passed_time":0.9546470244,"remaining_time":0.01159490313},
{"learn":[1352133.646],"iteration":988,"passed_time":0.9555258344,"remaining_time":0.01062768875},
{"learn":[1351820.684],"iteration":989,"passed_time":0.9564054776,"remaining_time":0.00966066139},
{"learn":[1351537.419],"iteration":990,"passed_time":0.9573030371,"remaining_time":0.008693973092},
{"learn":[1351160.97],"iteration":991,"passed_time":0.9581653058,"remaining_time":0.007727139563},
{"learn":[1350986.843],"iteration":992,"passed_time":0.9590479907,"remaining_time":0.006760660559},
{"learn":[1350712.661],"iteration":993,"passed_time":0.9601004627,"remaining_time":0.005795375026},
{"learn":[1350323.672],"iteration":994,"passed_time":0.9609677313,"remaining_time":0.004828983574},
{"learn":[1350131.477],"iteration":995,"passed_time":0.9619708713,"remaining_time":0.003863336832},
{"learn":[1349761.997],"iteration":996,"passed_time":0.9630105936,"remaining_time":0.002897724956},
{"learn":[1349597.617],"iteration":997,"passed_time":0.9638644876,"remaining_time":0.001931592159},
{"learn":[1349277.222],"iteration":998,"passed_time":0.9647437559,"remaining_time":0.0009657094653},
{"learn":[1349078.074],"iteration":999,"passed_time":0.9655804419,"remaining_time":0}
]}